tira_led/ws2812_codigo/rtl/ws2812_timer.v
// ============================================================
// ws2812_timer.v
// Base de tiempos para el protocolo WS2812 (NRZ de un solo hilo)
// Pensado para la Colorlight i9 (reloj de 25 MHz -> 40 ns/ciclo)
//
// Tiempos del WS2812B:
//   Bit '0':  T0H = 0.40 us  |  T0L = 0.85 us
//   Bit '1':  T1H = 0.80 us  |  T1L = 0.45 us
//   Periodo de bit ~= 1.25 us
//   RESET (latch): linea en bajo > 50 us
//
// A 25 MHz:
//   1.25 us = 31.25 ciclos -> usamos 31 (1.24 us, dentro de tolerancia)
//   0.40 us = 10 ciclos
//   0.80 us = 20 ciclos
//   RESET   = 2500 ciclos (100 us, con margen de sobra)
//
// Funcionamiento:
//   - 'run' habilita el conteo del periodo de bit.
//   - 'bit_in' indica que bit se esta transmitiendo (0/1).
//   - 'dout_level' entrega el nivel que debe tener la linea de datos.
//   - 'bit_done' se pulsa 1 ciclo al terminar cada periodo de bit.
//   - 'rst_req' pide generar el tiempo de RESET/latch; 'rst_done'
//     se pulsa 1 ciclo cuando el tiempo de latch termino.
// ============================================================
`timescale 1ns / 1ps

module ws2812_timer #(
    parameter CLK_HZ       = 25_000_000,
    parameter CYCLES_BIT   = 31,    // ~1.25 us
    parameter CYCLES_T0H   = 10,    // ~0.40 us
    parameter CYCLES_T1H   = 20,    // ~0.80 us
    parameter CYCLES_RESET = 2500   // ~100 us
)(
    input  wire clk,
    input  wire rst_n,      // reset asincrono activo en bajo

    input  wire run,        // habilita el conteo de bits
    input  wire bit_in,     // valor del bit a serializar
    input  wire rst_req,    // solicitar periodo de latch (linea en bajo)

    output wire dout_level, // nivel de la linea de datos WS2812
    output wire bit_done,   // pulso: ultimo ciclo de un periodo de bit
    output wire rst_done    // pulso: ultimo ciclo del periodo de latch
);

    // Ancho suficiente para el contador mas grande
    localparam CW = $clog2(CYCLES_RESET + 1);

    reg [CW-1:0] cnt;

    // 'bit_done' y 'rst_done' son COMBINACIONALES: se activan durante
    // el ultimo ciclo del periodo, de modo que la FSM que consume
    // estas senales cambie de estado en el MISMO flanco en que 'cnt'
    // da la vuelta. Asi no aparecen pulsos espurios en la linea al
    // pasar de un pixel al siguiente.
    assign bit_done = run     && (cnt == CYCLES_BIT   - 1);
    assign rst_done = rst_req && (cnt == CYCLES_RESET - 1);

    // ------------------------------------------------------------
    // Contador de periodo de bit / latch
    // ------------------------------------------------------------
    always @(posedge clk or negedge rst_n) begin
        if (!rst_n) begin
            cnt <= {CW{1'b0}};
        end else begin
            if (run) begin
                if (bit_done) cnt <= {CW{1'b0}};
                else          cnt <= cnt + 1'b1;
            end else if (rst_req) begin
                if (rst_done) cnt <= {CW{1'b0}};
                else          cnt <= cnt + 1'b1;
            end else begin
                cnt <= {CW{1'b0}};
            end
        end
    end

    // ------------------------------------------------------------
    // Nivel de salida: alto durante T0H o T1H segun el bit,
    // bajo el resto del periodo. En latch siempre bajo.
    // ------------------------------------------------------------
    wire [CW-1:0] t_high = bit_in ? CYCLES_T1H[CW-1:0] : CYCLES_T0H[CW-1:0];

    assign dout_level = run ? (cnt < t_high) : 1'b0;

endmodule

Proyecto_teclado/Modulos_litex/ws2812_codigo/rtl/ws2812_led.v
// ============================================================
// ws2812_led.v
// Serializador de 24 bits (formato GRB, MSB primero) para UN led
// WS2812. Usa ws2812_timer como base de tiempos.
//
// Protocolo de handshake:
//   - Cuando 'ready' = 1, el modulo puede aceptar un nuevo pixel.
//   - El usuario pone 'data' (24 bits GRB) y pulsa 'valid' 1 ciclo.
//   - El modulo serializa los 24 bits por 'dout'.
//   - Al terminar los 24 bits vuelve a 'ready' = 1 SIN soltar la
//     linea: si se encadenan pixeles seguidos, los bits salen
//     back-to-back (asi se cargan los 64 leds de la matriz).
//   - Si se pulsa 'latch' cuando ready=1, genera el periodo de
//     reset (>50us en bajo) y pulsa 'latch_done'.
//
// Nota de formato: el WS2812 recibe primero G7..G0, luego R7..R0
// y por ultimo B7..B0. Aqui 'data' ya se asume en orden GRB:
//   data[23:16] = G, data[15:8] = R, data[7:0] = B
// ============================================================
`timescale 1ns / 1ps

module ws2812_led #(
    parameter CYCLES_BIT   = 31,
    parameter CYCLES_T0H   = 10,
    parameter CYCLES_T1H   = 20,
    parameter CYCLES_RESET = 2500
)(
    input  wire        clk,
    input  wire        rst_n,

    input  wire [23:0] data,       // pixel GRB
    input  wire        valid,      // pulso: cargar y transmitir 'data'
    input  wire        latch,      // pulso: generar tiempo de reset
    output wire        ready,      // 1 = listo para nuevo pixel/latch
    output reg         latch_done, // pulso: latch terminado

    output wire        dout        // linea de datos hacia la tira/matriz
);

    // ------------------- FSM -------------------
    localparam [1:0] S_IDLE  = 2'd0,
                     S_SHIFT = 2'd1,
                     S_LATCH = 2'd2;

    reg [1:0]  state;
    reg [23:0] shreg;    // registro de desplazamiento (MSB primero)
    reg [4:0]  bit_cnt;  // 0..23

    wire bit_done, rst_done;

    assign ready = (state == S_IDLE);

    // Bit actual = MSB del registro de desplazamiento
    wire cur_bit = shreg[23];

    // ------------------- Timer -------------------
    ws2812_timer #(
        .CYCLES_BIT  (CYCLES_BIT),
        .CYCLES_T0H  (CYCLES_T0H),
        .CYCLES_T1H  (CYCLES_T1H),
        .CYCLES_RESET(CYCLES_RESET)
    ) u_timer (
        .clk       (clk),
        .rst_n     (rst_n),
        .run       (state == S_SHIFT),
        .bit_in    (cur_bit),
        .rst_req   (state == S_LATCH),
        .dout_level(dout),
        .bit_done  (bit_done),
        .rst_done  (rst_done)
    );

    // ------------------- Control -------------------
    always @(posedge clk or negedge rst_n) begin
        if (!rst_n) begin
            state      <= S_IDLE;
            shreg      <= 24'd0;
            bit_cnt    <= 5'd0;
            latch_done <= 1'b0;
        end else begin
            latch_done <= 1'b0;

            case (state)
                S_IDLE: begin
                    if (valid) begin
                        shreg   <= data;
                        bit_cnt <= 5'd0;
                        state   <= S_SHIFT;
                    end else if (latch) begin
                        state <= S_LATCH;
                    end
                end

                S_SHIFT: begin
                    if (bit_done) begin
                        if (bit_cnt == 5'd23) begin
                            state <= S_IDLE;   // pixel completo
                        end else begin
                            shreg   <= {shreg[22:0], 1'b0};
                            bit_cnt <= bit_cnt + 1'b1;
                        end
                    end
                end

                S_LATCH: begin
                    if (rst_done) begin
                        latch_done <= 1'b1;
                        state      <= S_IDLE;
                    end
                end

                default: state <= S_IDLE;
            endcase
        end
    end

endmodule

I2C/ws2812_codigo/tb/tb_ws2812_led.v
// ============================================================
// tb_ws2812_led.v
// Envia dos pixeles conocidos al serializador y DECODIFICA la
// forma de onda de 'dout' midiendo el ancho de cada pulso alto:
//   ancho > 600 ns -> bit '1', ancho < 600 ns -> bit '0'
// Luego compara los 24 bits recuperados con el dato original.
// Tambien verifica el handshake ready/valid y el latch.
// ============================================================
`timescale 1ns / 1ps

module tb_ws2812_led;

    localparam CLK_PERIOD = 40; // 25 MHz

    reg         clk = 0;
    reg         rst_n = 0;
    reg  [23:0] data = 0;
    reg         valid = 0;
    reg         latch = 0;
    wire        ready, latch_done, dout;

    integer errors = 0;

    ws2812_led dut (
        .clk(clk), .rst_n(rst_n),
        .data(data), .valid(valid), .latch(latch),
        .ready(ready), .latch_done(latch_done), .dout(dout)
    );

    always #(CLK_PERIOD/2) clk = ~clk;

    // ------------------------------------------------------------
    // Decodificador: mide 24 pulsos y reconstruye la palabra
    // ------------------------------------------------------------
    task decode_pixel(output [23:0] rx);
        integer  i, width;
        realtime t_rise, t_fall;
        begin
            rx = 24'd0;
            for (i = 0; i < 24; i = i + 1) begin
                @(posedge dout);  t_rise = $realtime;
                @(negedge dout);  t_fall = $realtime;
                width = t_fall - t_rise;
                rx = {rx[22:0], (width > 600) ? 1'b1 : 1'b0};
            end
        end
    endtask

    // ------------------------------------------------------------
    // Tarea: enviar un pixel y verificar lo decodificado
    // ------------------------------------------------------------
    task send_and_check(input [23:0] px);
        reg [23:0] rx;
        begin
            wait (ready);
            @(posedge clk);
            data  <= px;
            valid <= 1'b1;
            @(posedge clk);
            valid <= 1'b0;

            decode_pixel(rx);
            $display("Enviado: %06h  |  Decodificado: %06h  %s",
                     px, rx, (rx === px) ? "[OK]" : "[ERROR]");
            if (rx !== px) errors = errors + 1;
        end
    endtask

    // ------------------------------------------------------------
    // Estimulo principal
    // ------------------------------------------------------------
    realtime t0, t1;
    initial begin
        $dumpfile("tb_ws2812_led.vcd");
        $dumpvars(0, tb_ws2812_led);

        repeat (4) @(posedge clk);
        rst_n = 1;

        // Prueba 1: patron alternado
        send_and_check(24'hA5C3F0);

        // Prueba 2: otro patron (verde puro en GRB)
        send_and_check(24'hFF0000);

        // Prueba 3: ready debe volver a 1 al terminar
        wait (ready);
        $display("Handshake: ready volvio a 1 tras el pixel [OK]");

        // Prueba 4: latch >= 50 us
        @(posedge clk);
        t0 = $realtime;
        latch <= 1'b1;
        @(posedge clk);
        latch <= 1'b0;
        @(posedge latch_done);
        t1 = $realtime;
        $display("Latch: %0d ns (minimo 50000)", t1 - t0);
        if (t1 - t0 < 50000) begin
            $display("  ERROR: latch demasiado corto");
            errors = errors + 1;
        end
        if (dout !== 1'b0) begin
            $display("  ERROR: dout deberia permanecer en 0 durante el latch");
            errors = errors + 1;
        end

        if (errors == 0) $display("\n== TB_LED: TODAS LAS PRUEBAS PASARON ==");
        else             $display("\n== TB_LED: %0d ERRORES ==", errors);
        $finish;
    end

    // Timeout de seguridad
    initial begin
        #2_000_000;
        $display("ERROR: timeout de simulacion");
        $finish;
    end

endmodule

tira_led/ws2812_codigo/sim/tb_ws2812_led.vcd
$date
	Thu Jul 16 10:38:24 2026
$end
$version
	Icarus Verilog
$end
$timescale
	1ps
$end
$scope module tb_ws2812_led $end
$var wire 1 ! ready $end
$var wire 1 " latch_done $end
$var wire 1 # dout $end
$var parameter 32 $ CLK_PERIOD $end
$var reg 1 % clk $end
$var reg 24 & data [23:0] $end
$var reg 1 ' latch $end
$var reg 1 ( rst_n $end
$var reg 1 ) valid $end
$var integer 32 * errors [31:0] $end
$var real 1 + t0 $end
$var real 1 , t1 $end
$scope module dut $end
$var wire 1 % clk $end
$var wire 24 - data [23:0] $end
$var wire 1 ' latch $end
$var wire 1 ( rst_n $end
$var wire 1 ) valid $end
$var wire 1 . rst_done $end
$var wire 1 ! ready $end
$var wire 1 # dout $end
$var wire 1 / cur_bit $end
$var wire 1 0 bit_done $end
$var parameter 32 1 CYCLES_BIT $end
$var parameter 32 2 CYCLES_RESET $end
$var parameter 32 3 CYCLES_T0H $end
$var parameter 32 4 CYCLES_T1H $end
$var parameter 2 5 S_IDLE $end
$var parameter 2 6 S_LATCH $end
$var parameter 2 7 S_SHIFT $end
$var reg 5 8 bit_cnt [4:0] $end
$var reg 1 " latch_done $end
$var reg 24 9 shreg [23:0] $end
$var reg 2 : state [1:0] $end
$scope module u_timer $end
$var wire 1 0 bit_done $end
$var wire 1 / bit_in $end
$var wire 1 % clk $end
$var wire 1 . rst_done $end
$var wire 1 ( rst_n $end
$var wire 1 ; rst_req $end
$var wire 1 < run $end
$var wire 12 = t_high [11:0] $end
$var wire 1 # dout_level $end
$var parameter 32 > CLK_HZ $end
$var parameter 32 ? CW $end
$var parameter 32 @ CYCLES_BIT $end
$var parameter 32 A CYCLES_RESET $end
$var parameter 32 B CYCLES_T0H $end
$var parameter 32 C CYCLES_T1H $end
$var reg 12 D cnt [11:0] $end
$upscope $end
$upscope $end
$scope task decode_pixel $end
$var reg 24 E rx [23:0] $end
$var integer 32 F i [31:0] $end
$var real 1 G t_fall $end
$var real 1 H t_rise $end
$var integer 32 I width [31:0] $end
$upscope $end
$scope task send_and_check $end
$var reg 24 J px [23:0] $end
$var reg 24 K rx [23:0] $end
$upscope $end
$upscope $end
$enddefinitions $end
$comment Show the parameter values. $end
$dumpall
b10100 C
b1010 B
b100111000100 A
b11111 @
b1100 ?
b1011111010111100001000000 >
b1 7
b10 6
b0 5
b10100 4
b1010 3
b100111000100 2
b11111 1
b101000 $
$end
#0
$dumpvars
bx K
bx J
bx I
r0 H
r0 G
bx F
bx E
bx D
b0xxxx0 =
x<
x;
bx :
bx 9
bx 8
x0
x/
x.
b0 -
r0 ,
r0 +
b0 *
0)
0(
0'
b0 &
0%
x#
x"
x!
$end
#20000
b1010 =
0/
00
0#
0.
b0 D
0"
b0 8
b0 9
1!
0<
0;
b0 :
1%
#40000
0%
#60000
1%
#80000
0%
#100000
1%
#120000
0%
#140000
b101001011100001111110000 J
1(
1%
#160000
0%
#180000
1)
b101001011100001111110000 &
b101001011100001111110000 -
1%
#200000
0%
#220000
r220 H
b10100 =
1#
1/
0!
1<
b1 :
b101001011100001111110000 9
0)
b0 F
b0 E
1%
#240000
0%
#260000
b1 D
1%
#280000
0%
#300000
b10 D
1%
#320000
0%
#340000
b11 D
1%
#360000
0%
#380000
b100 D
1%
#400000
0%
#420000
b101 D
1%
#440000
0%
#460000
b110 D
1%
#480000
0%
#500000
b111 D
1%
#520000
0%
#540000
b1000 D
1%
#560000
0%
#580000
b1001 D
1%
#600000
0%
#620000
b1010 D
1%
#640000
0%
#660000
b1011 D
1%
#680000
0%
#700000
b1100 D
1%
#720000
0%
#740000
b1101 D
1%
#760000
0%
#780000
b1110 D
1%
#800000
0%
#820000
b1111 D
1%
#840000
0%
#860000
b10000 D
1%
#880000
0%
#900000
b10001 D
1%
#920000
0%
#940000
b10010 D
1%
#960000
0%
#980000
b10011 D
1%
#1000000
0%
#1020000
b1 F
b1 E
b1100100000 I
r1020 G
0#
b10100 D
1%
#1040000
0%
#1060000
b10101 D
1%
#1080000
0%
#1100000
b10110 D
1%
#1120000
0%
#1140000
b10111 D
1%
#1160000
0%
#1180000
b11000 D
1%
#1200000
0%
#1220000
b11001 D
1%
#1240000
0%
#1260000
b11010 D
1%
#1280000
0%
#1300000
b11011 D
1%
#1320000
0%
#1340000
b11100 D
1%
#1360000
0%
#1380000
b11101 D
1%
#1400000
0%
#1420000
10
b11110 D
1%
#1440000
0%
#1460000
r1460 H
b1010 =
00
1#
0/
b0 D
b1 8
b10010111000011111100000 9
1%
#1480000
0%
#1500000
b1 D
1%
#1520000
0%
#1540000
b10 D
1%
#1560000
0%
#1580000
b11 D
1%
#1600000
0%
#1620000
b100 D
1%
#1640000
0%
#1660000
b101 D
1%
#1680000
0%
#1700000
b110 D
1%
#1720000
0%
#1740000
b111 D
1%
#1760000
0%
#1780000
b1000 D
1%
#1800000
0%
#1820000
b1001 D
1%
#1840000
0%
#1860000
b10 F
b10 E
b110010000 I
r1860 G
0#
b1010 D
1%
#1880000
0%
#1900000
b1011 D
1%
#1920000
0%
#1940000
b1100 D
1%
#1960000
0%
#1980000
b1101 D
1%
#2000000
0%
#2020000
b1110 D
1%
#2040000
0%
#2060000
b1111 D
1%
#2080000
0%
#2100000
b10000 D
1%
#2120000
0%
#2140000
b10001 D
1%
#2160000
0%
#2180000
b10010 D
1%
#2200000
0%
#2220000
b10011 D
1%
#2240000
0%
#2260000
b10100 D
1%
#2280000
0%
#2300000
b10101 D
1%
#2320000
0%
#2340000
b10110 D
1%
#2360000
0%
#2380000
b10111 D
1%
#2400000
0%
#2420000
b11000 D
1%
#2440000
0%
#2460000
b11001 D
1%
#2480000
0%
#2500000
b11010 D
1%
#2520000
0%
#2540000
b11011 D
1%
#2560000
0%
#2580000
b11100 D
1%
#2600000
0%
#2620000
b11101 D
1%
#2640000
0%
#2660000
10
b11110 D
1%
#2680000
0%
#2700000
b10100 =
r2700 H
1/
00
1#
b10 8
b100101110000111111000000 9
b0 D
1%
#2720000
0%
#2740000
b1 D
1%
#2760000
0%
#2780000
b10 D
1%
#2800000
0%
#2820000
b11 D
1%
#2840000
0%
#2860000
b100 D
1%
#2880000
0%
#2900000
b101 D
1%
#2920000
0%
#2940000
b110 D
1%
#2960000
0%
#2980000
b111 D
1%
#3000000
0%
#3020000
b1000 D
1%
#3040000
0%
#3060000
b1001 D
1%
#3080000
0%
#3100000
b1010 D
1%
#3120000
0%
#3140000
b1011 D
1%
#3160000
0%
#3180000
b1100 D
1%
#3200000
0%
#3220000
b1101 D
1%
#3240000
0%
#3260000
b1110 D
1%
#3280000
0%
#3300000
b1111 D
1%
#3320000
0%
#3340000
b10000 D
1%
#3360000
0%
#3380000
b10001 D
1%
#3400000
0%
#3420000
b10010 D
1%
#3440000
0%
#3460000
b10011 D
1%
#3480000
0%
#3500000
b11 F
b101 E
b1100100000 I
r3500 G
0#
b10100 D
1%
#3520000
0%
#3540000
b10101 D
1%
#3560000
0%
#3580000
b10110 D
1%
#3600000
0%
#3620000
b10111 D
1%
#3640000
0%
#3660000
b11000 D
1%
#3680000
0%
#3700000
b11001 D
1%
#3720000
0%
#3740000
b11010 D
1%
#3760000
0%
#3780000
b11011 D
1%
#3800000
0%
#3820000
b11100 D
1%
#3840000
0%
#3860000
b11101 D
1%
#3880000
0%
#3900000
10
b11110 D
1%
#3920000
0%
#3940000
r3940 H
b1010 =
00
1#
0/
b0 D
b11 8
b1011100001111110000000 9
1%
#3960000
0%
#3980000
b1 D
1%
#4000000
0%
#4020000
b10 D
1%
#4040000
0%
#4060000
b11 D
1%
#4080000
0%
#4100000
b100 D
1%
#4120000
0%
#4140000
b101 D
1%
#4160000
0%
#4180000
b110 D
1%
#4200000
0%
#4220000
b111 D
1%
#4240000
0%
#4260000
b1000 D
1%
#4280000
0%
#4300000
b1001 D
1%
#4320000
0%
#4340000
b100 F
b1010 E
b110010000 I
r4340 G
0#
b1010 D
1%
#4360000
0%
#4380000
b1011 D
1%
#4400000
0%
#4420000
b1100 D
1%
#4440000
0%
#4460000
b1101 D
1%
#4480000
0%
#4500000
b1110 D
1%
#4520000
0%
#4540000
b1111 D
1%
#4560000
0%
#4580000
b10000 D
1%
#4600000
0%
#4620000
b10001 D
1%
#4640000
0%
#4660000
b10010 D
1%
#4680000
0%
#4700000
b10011 D
1%
#4720000
0%
#4740000
b10100 D
1%
#4760000
0%
#4780000
b10101 D
1%
#4800000
0%
#4820000
b10110 D
1%
#4840000
0%
#4860000
b10111 D
1%
#4880000
0%
#4900000
b11000 D
1%
#4920000
0%
#4940000
b11001 D
1%
#4960000
0%
#4980000
b11010 D
1%
#5000000
0%
#5020000
b11011 D
1%
#5040000
0%
#5060000
b11100 D
1%
#5080000
0%
#5100000
b11101 D
1%
#5120000
0%
#5140000
10
b11110 D
1%
#5160000
0%
#5180000
r5180 H
00
1#
b100 8
b10111000011111100000000 9
b0 D
1%
#5200000
0%
#5220000
b1 D
1%
#5240000
0%
#5260000
b10 D
1%
#5280000
0%
#5300000
b11 D
1%
#5320000
0%
#5340000
b100 D
1%
#5360000
0%
#5380000
b101 D
1%
#5400000
0%
#5420000
b110 D
1%
#5440000
0%
#5460000
b111 D
1%
#5480000
0%
#5500000
b1000 D
1%
#5520000
0%
#5540000
b1001 D
1%
#5560000
0%
#5580000
b101 F
b10100 E
r5580 G
0#
b1010 D
1%
#5600000
0%
#5620000
b1011 D
1%
#5640000
0%
#5660000
b1100 D
1%
#5680000
0%
#5700000
b1101 D
1%
#5720000
0%
#5740000
b1110 D
1%
#5760000
0%
#5780000
b1111 D
1%
#5800000
0%
#5820000
b10000 D
1%
#5840000
0%
#5860000
b10001 D
1%
#5880000
0%
#5900000
b10010 D
1%
#5920000
0%
#5940000
b10011 D
1%
#5960000
0%
#5980000
b10100 D
1%
#6000000
0%
#6020000
b10101 D
1%
#6040000
0%
#6060000
b10110 D
1%
#6080000
0%
#6100000
b10111 D
1%
#6120000
0%
#6140000
b11000 D
1%
#6160000
0%
#6180000
b11001 D
1%
#6200000
0%
#6220000
b11010 D
1%
#6240000
0%
#6260000
b11011 D
1%
#6280000
0%
#6300000
b11100 D
1%
#6320000
0%
#6340000
b11101 D
1%
#6360000
0%
#6380000
10
b11110 D
1%
#6400000
0%
#6420000
r6420 H
b10100 =
00
1#
1/
b0 D
b101 8
b101110000111111000000000 9
1%
#6440000
0%
#6460000
b1 D
1%
#6480000
0%
#6500000
b10 D
1%
#6520000
0%
#6540000
b11 D
1%
#6560000
0%
#6580000
b100 D
1%
#6600000
0%
#6620000
b101 D
1%
#6640000
0%
#6660000
b110 D
1%
#6680000
0%
#6700000
b111 D
1%
#6720000
0%
#6740000
b1000 D
1%
#6760000
0%
#6780000
b1001 D
1%
#6800000
0%
#6820000
b1010 D
1%
#6840000
0%
#6860000
b1011 D
1%
#6880000
0%
#6900000
b1100 D
1%
#6920000
0%
#6940000
b1101 D
1%
#6960000
0%
#6980000
b1110 D
1%
#7000000
0%
#7020000
b1111 D
1%
#7040000
0%
#7060000
b10000 D
1%
#7080000
0%
#7100000
b10001 D
1%
#7120000
0%
#7140000
b10010 D
1%
#7160000
0%
#7180000
b10011 D
1%
#7200000
0%
#7220000
b110 F
b101001 E
b1100100000 I
r7220 G
0#
b10100 D
1%
#7240000
0%
#7260000
b10101 D
1%
#7280000
0%
#7300000
b10110 D
1%
#7320000
0%
#7340000
b10111 D
1%
#7360000
0%
#7380000
b11000 D
1%
#7400000
0%
#7420000
b11001 D
1%
#7440000
0%
#7460000
b11010 D
1%
#7480000
0%
#7500000
b11011 D
1%
#7520000
0%
#7540000
b11100 D
1%
#7560000
0%
#7580000
b11101 D
1%
#7600000
0%
#7620000
10
b11110 D
1%
#7640000
0%
#7660000
b1010 =
r7660 H
0/
00
1#
b110 8
b11100001111110000000000 9
b0 D
1%
#7680000
0%
#7700000
b1 D
1%
#7720000
0%
#7740000
b10 D
1%
#7760000
0%
#7780000
b11 D
1%
#7800000
0%
#7820000
b100 D
1%
#7840000
0%
#7860000
b101 D
1%
#7880000
0%
#7900000
b110 D
1%
#7920000
0%
#7940000
b111 D
1%
#7960000
0%
#7980000
b1000 D
1%
#8000000
0%
#8020000
b1001 D
1%
#8040000
0%
#8060000
b111 F
b1010010 E
b110010000 I
r8060 G
0#
b1010 D
1%
#8080000
0%
#8100000
b1011 D
1%
#8120000
0%
#8140000
b1100 D
1%
#8160000
0%
#8180000
b1101 D
1%
#8200000
0%
#8220000
b1110 D
1%
#8240000
0%
#8260000
b1111 D
1%
#8280000
0%
#8300000
b10000 D
1%
#8320000
0%
#8340000
b10001 D
1%
#8360000
0%
#8380000
b10010 D
1%
#8400000
0%
#8420000
b10011 D
1%
#8440000
0%
#8460000
b10100 D
1%
#8480000
0%
#8500000
b10101 D
1%
#8520000
0%
#8540000
b10110 D
1%
#8560000
0%
#8580000
b10111 D
1%
#8600000
0%
#8620000
b11000 D
1%
#8640000
0%
#8660000
b11001 D
1%
#8680000
0%
#8700000
b11010 D
1%
#8720000
0%
#8740000
b11011 D
1%
#8760000
0%
#8780000
b11100 D
1%
#8800000
0%
#8820000
b11101 D
1%
#8840000
0%
#8860000
10
b11110 D
1%
#8880000
0%
#8900000
r8900 H
b10100 =
00
1#
1/
b0 D
b111 8
b111000011111100000000000 9
1%
#8920000
0%
#8940000
b1 D
1%
#8960000
0%
#8980000
b10 D
1%
#9000000
0%
#9020000
b11 D
1%
#9040000
0%
#9060000
b100 D
1%
#9080000
0%
#9100000
b101 D
1%
#9120000
0%
#9140000
b110 D
1%
#9160000
0%
#9180000
b111 D
1%
#9200000
0%
#9220000
b1000 D
1%
#9240000
0%
#9260000
b1001 D
1%
#9280000
0%
#9300000
b1010 D
1%
#9320000
0%
#9340000
b1011 D
1%
#9360000
0%
#9380000
b1100 D
1%
#9400000
0%
#9420000
b1101 D
1%
#9440000
0%
#9460000
b1110 D
1%
#9480000
0%
#9500000
b1111 D
1%
#9520000
0%
#9540000
b10000 D
1%
#9560000
0%
#9580000
b10001 D
1%
#9600000
0%
#9620000
b10010 D
1%
#9640000
0%
#9660000
b10011 D
1%
#9680000
0%
#9700000
b1000 F
b10100101 E
b1100100000 I
r9700 G
0#
b10100 D
1%
#9720000
0%
#9740000
b10101 D
1%
#9760000
0%
#9780000
b10110 D
1%
#9800000
0%
#9820000
b10111 D
1%
#9840000
0%
#9860000
b11000 D
1%
#9880000
0%
#9900000
b11001 D
1%
#9920000
0%
#9940000
b11010 D
1%
#9960000
0%
#9980000
b11011 D
1%
#10000000
0%
#10020000
b11100 D
1%
#10040000
0%
#10060000
b11101 D
1%
#10080000
0%
#10100000
10
b11110 D
1%
#10120000
0%
#10140000
r10140 H
00
1#
b1000 8
b110000111111000000000000 9
b0 D
1%
#10160000
0%
#10180000
b1 D
1%
#10200000
0%
#10220000
b10 D
1%
#10240000
0%
#10260000
b11 D
1%
#10280000
0%
#10300000
b100 D
1%
#10320000
0%
#10340000
b101 D
1%
#10360000
0%
#10380000
b110 D
1%
#10400000
0%
#10420000
b111 D
1%
#10440000
0%
#10460000
b1000 D
1%
#10480000
0%
#10500000
b1001 D
1%
#10520000
0%
#10540000
b1010 D
1%
#10560000
0%
#10580000
b1011 D
1%
#10600000
0%
#10620000
b1100 D
1%
#10640000
0%
#10660000
b1101 D
1%
#10680000
0%
#10700000
b1110 D
1%
#10720000
0%
#10740000
b1111 D
1%
#10760000
0%
#10780000
b10000 D
1%
#10800000
0%
#10820000
b10001 D
1%
#10840000
0%
#10860000
b10010 D
1%
#10880000
0%
#10900000
b10011 D
1%
#10920000
0%
#10940000
b1001 F
b101001011 E
r10940 G
0#
b10100 D
1%
#10960000
0%
#10980000
b10101 D
1%
#11000000
0%
#11020000
b10110 D
1%
#11040000
0%
#11060000
b10111 D
1%
#11080000
0%
#11100000
b11000 D
1%
#11120000
0%
#11140000
b11001 D
1%
#11160000
0%
#11180000
b11010 D
1%
#11200000
0%
#11220000
b11011 D
1%
#11240000
0%
#11260000
b11100 D
1%
#11280000
0%
#11300000
b11101 D
1%
#11320000
0%
#11340000
10
b11110 D
1%
#11360000
0%
#11380000
r11380 H
00
1#
b0 D
b1001 8
b100001111110000000000000 9
1%
#11400000
0%
#11420000
b1 D
1%
#11440000
0%
#11460000
b10 D
1%
#11480000
0%
#11500000
b11 D
1%
#11520000
0%
#11540000
b100 D
1%
#11560000
0%
#11580000
b101 D
1%
#11600000
0%
#11620000
b110 D
1%
#11640000
0%
#11660000
b111 D
1%
#11680000
0%
#11700000
b1000 D
1%
#11720000
0%
#11740000
b1001 D
1%
#11760000
0%
#11780000
b1010 D
1%
#11800000
0%
#11820000
b1011 D
1%
#11840000
0%
#11860000
b1100 D
1%
#11880000
0%
#11900000
b1101 D
1%
#11920000
0%
#11940000
b1110 D
1%
#11960000
0%
#11980000
b1111 D
1%
#12000000
0%
#12020000
b10000 D
1%
#12040000
0%
#12060000
b10001 D
1%
#12080000
0%
#12100000
b10010 D
1%
#12120000
0%
#12140000
b10011 D
1%
#12160000
0%
#12180000
b1010 F
b1010010111 E
r12180 G
0#
b10100 D
1%
#12200000
0%
#12220000
b10101 D
1%
#12240000
0%
#12260000
b10110 D
1%
#12280000
0%
#12300000
b10111 D
1%
#12320000
0%
#12340000
b11000 D
1%
#12360000
0%
#12380000
b11001 D
1%
#12400000
0%
#12420000
b11010 D
1%
#12440000
0%
#12460000
b11011 D
1%
#12480000
0%
#12500000
b11100 D
1%
#12520000
0%
#12540000
b11101 D
1%
#12560000
0%
#12580000
10
b11110 D
1%
#12600000
0%
#12620000
b1010 =
r12620 H
0/
00
1#
b1010 8
b11111100000000000000 9
b0 D
1%
#12640000
0%
#12660000
b1 D
1%
#12680000
0%
#12700000
b10 D
1%
#12720000
0%
#12740000
b11 D
1%
#12760000
0%
#12780000
b100 D
1%
#12800000
0%
#12820000
b101 D
1%
#12840000
0%
#12860000
b110 D
1%
#12880000
0%
#12900000
b111 D
1%
#12920000
0%
#12940000
b1000 D
1%
#12960000
0%
#12980000
b1001 D
1%
#13000000
0%
#13020000
b1011 F
b10100101110 E
b110010000 I
r13020 G
0#
b1010 D
1%
#13040000
0%
#13060000
b1011 D
1%
#13080000
0%
#13100000
b1100 D
1%
#13120000
0%
#13140000
b1101 D
1%
#13160000
0%
#13180000
b1110 D
1%
#13200000
0%
#13220000
b1111 D
1%
#13240000
0%
#13260000
b10000 D
1%
#13280000
0%
#13300000
b10001 D
1%
#13320000
0%
#13340000
b10010 D
1%
#13360000
0%
#13380000
b10011 D
1%
#13400000
0%
#13420000
b10100 D
1%
#13440000
0%
#13460000
b10101 D
1%
#13480000
0%
#13500000
b10110 D
1%
#13520000
0%
#13540000
b10111 D
1%
#13560000
0%
#13580000
b11000 D
1%
#13600000
0%
#13620000
b11001 D
1%
#13640000
0%
#13660000
b11010 D
1%
#13680000
0%
#13700000
b11011 D
1%
#13720000
0%
#13740000
b11100 D
1%
#13760000
0%
#13780000
b11101 D
1%
#13800000
0%
#13820000
10
b11110 D
1%
#13840000
0%
#13860000
r13860 H
00
1#
b0 D
b1011 8
b111111000000000000000 9
1%
#13880000
0%
#13900000
b1 D
1%
#13920000
0%
#13940000
b10 D
1%
#13960000
0%
#13980000
b11 D
1%
#14000000
0%
#14020000
b100 D
1%
#14040000
0%
#14060000
b101 D
1%
#14080000
0%
#14100000
b110 D
1%
#14120000
0%
#14140000
b111 D
1%
#14160000
0%
#14180000
b1000 D
1%
#14200000
0%
#14220000
b1001 D
1%
#14240000
0%
#14260000
b1100 F
b101001011100 E
r14260 G
0#
b1010 D
1%
#14280000
0%
#14300000
b1011 D
1%
#14320000
0%
#14340000
b1100 D
1%
#14360000
0%
#14380000
b1101 D
1%
#14400000
0%
#14420000
b1110 D
1%
#14440000
0%
#14460000
b1111 D
1%
#14480000
0%
#14500000
b10000 D
1%
#14520000
0%
#14540000
b10001 D
1%
#14560000
0%
#14580000
b10010 D
1%
#14600000
0%
#14620000
b10011 D
1%
#14640000
0%
#14660000
b10100 D
1%
#14680000
0%
#14700000
b10101 D
1%
#14720000
0%
#14740000
b10110 D
1%
#14760000
0%
#14780000
b10111 D
1%
#14800000
0%
