I2C/Codigo/i2c_slave.v
//==============================================================================
// i2c_slave.v
// Esclavo I2C implementado con una Maquina de Estados Finitos (FSM)
//
// - Detecta las condiciones de START y STOP observando SDA mientras SCL=1
// - Recibe la direccion de 7 bits + bit R/W y responde ACK si coincide
//   con su parametro ADDR (como en el diagrama: el ACK lo genera el esclavo)
// - Escritura del maestro : recibe bytes (D7..D0) y responde ACK tras cada uno
// - Lectura del maestro   : transmite 'data_tx' bit a bit y revisa el
//   ACK/NACK del maestro (NACK = fin de la lectura)
// - SDA cambia solo con SCL bajo y se muestrea en el flanco de subida de SCL
//   (el dato permanece estable durante el pulso alto de SCL)
//
// El esclavo NO genera SCL (no implementa clock stretching); solo lo observa.
//==============================================================================
module i2c_slave #(
    parameter [6:0] ADDR = 7'b1100100    // 0x64, como en el diagrama (1100100x)
)(
    input  wire       clk,        // reloj del sistema (para sincronizar)
    input  wire       rst_n,
    input  wire       scl,        // el esclavo solo escucha SCL
    inout  wire       sda,
    input  wire [7:0] data_tx,    // byte que enviara cuando el maestro lea
    output reg  [7:0] data_rx,    // ultimo byte recibido del maestro
    output reg        rx_valid    // pulso: 'data_rx' es valido
);

    //-------------------------------------------------------------------------
    // Salida de drenador abierto
    //-------------------------------------------------------------------------
    reg sda_o;
    assign sda = sda_o ? 1'bz : 1'b0;

    //-------------------------------------------------------------------------
    // Sincronizadores y deteccion de flancos / condiciones START-STOP
    //-------------------------------------------------------------------------
    reg [2:0] scl_s, sda_s;
    always @(posedge clk or negedge rst_n) begin
        if (!rst_n) begin
            scl_s <= 3'b111;
            sda_s <= 3'b111;
        end else begin
            scl_s <= {scl_s[1:0], scl};
            sda_s <= {sda_s[1:0], sda};
        end
    end

    wire scl_rise = (scl_s[2:1] == 2'b01);                 // flanco subida SCL
    wire scl_fall = (scl_s[2:1] == 2'b10);                 // flanco bajada SCL
    wire start_c  = scl_s[2] & scl_s[1] &  sda_s[2] & ~sda_s[1]; // SDA cae, SCL=1
    wire stop_c   = scl_s[2] & scl_s[1] & ~sda_s[2] &  sda_s[1]; // SDA sube, SCL=1

    //-------------------------------------------------------------------------
    // Estados de la FSM
    //-------------------------------------------------------------------------
    localparam [2:0] S_IDLE = 3'd0,   // espera condicion de START
                     S_ADDR = 3'd1,   // recibe direccion + R/W
                     S_ACKA = 3'd2,   // genera ACK de direccion
                     S_RX   = 3'd3,   // recibe byte de datos (maestro escribe)
                     S_ACKR = 3'd4,   // genera ACK del dato recibido
                     S_TX   = 3'd5,   // transmite byte de datos (maestro lee)
                     S_ACKM = 3'd6,   // lee ACK/NACK del maestro
                     S_WAIT = 3'd7;   // ignora el bus hasta STOP/START

    reg [2:0] st;
    reg [3:0] bit_cnt;
    reg [7:0] sh;         // registro de desplazamiento
    reg       rw;         // bit R/W recibido
    reg       mack;       // ACK/NACK muestreado del maestro

    always @(posedge clk or negedge rst_n) begin
        if (!rst_n) begin
            st       <= S_IDLE;
            sda_o    <= 1'b1;
            bit_cnt  <= 4'd0;
            sh       <= 8'h00;
            rw       <= 1'b0;
            mack     <= 1'b1;
            data_rx  <= 8'h00;
            rx_valid <= 1'b0;
        end else begin
            rx_valid <= 1'b0;                  // pulso de 1 ciclo

            if (start_c) begin                 // START (o START repetido)
                st      <= S_ADDR;
                bit_cnt <= 4'd0;
                sda_o   <= 1'b1;
            end else if (stop_c) begin         // STOP -> reposo
                st    <= S_IDLE;
                sda_o <= 1'b1;
            end else begin
                case (st)
                //-------------------------------------------- reposo
                S_IDLE: sda_o <= 1'b1;

                //-------------------------------------------- direccion + R/W
                S_ADDR: begin
                    if (scl_rise) begin
                        sh      <= {sh[6:0], sda_s[1]};    // muestrea con SCL=1
                        bit_cnt <= bit_cnt + 1'b1;
                    end else if (scl_fall && bit_cnt == 4'd8) begin
                        if (sh[7:1] == ADDR) begin         // ¿es para mi?
                            rw    <= sh[0];
                            sda_o <= 1'b0;                 // ACK (SDA a 0)
                            st    <= S_ACKA;
                        end else
                            st <= S_WAIT;                  // no es mi direccion
                    end
                end

                //-------------------------------------------- fin del ACK addr
                S_ACKA: if (scl_fall) begin
                    bit_cnt <= 4'd0;
                    if (rw) begin                          // maestro LEE
                        sh    <= data_tx;
                        sda_o <= data_tx[7];               // coloca D7
                        st    <= S_TX;
                    end else begin                         // maestro ESCRIBE
                        sda_o <= 1'b1;                     // libera SDA
                        st    <= S_RX;
                    end
                end

                //-------------------------------------------- recepcion de byte
                S_RX: begin
                    if (scl_rise) begin
                        sh      <= {sh[6:0], sda_s[1]};
                        bit_cnt <= bit_cnt + 1'b1;
                    end else if (scl_fall && bit_cnt == 4'd8) begin
                        data_rx  <= sh;
                        rx_valid <= 1'b1;
                        sda_o    <= 1'b0;                  // ACK
                        bit_cnt  <= 4'd0;
                        st       <= S_ACKR;
                    end
                end

                //-------------------------------------------- fin del ACK dato
                S_ACKR: if (scl_fall) begin
                    sda_o <= 1'b1;                         // libera SDA
                    st    <= S_RX;                         // admite mas bytes
                end

                //-------------------------------------------- transmision de byte
                S_TX: begin
                    if (scl_rise)
                        bit_cnt <= bit_cnt + 1'b1;
                    else if (scl_fall) begin
                        if (bit_cnt == 4'd8) begin
                            sda_o   <= 1'b1;               // libera para ACK
                            bit_cnt <= 4'd0;
                            st      <= S_ACKM;
                        end else begin
                            sda_o <= sh[6];                // siguiente bit
                            sh    <= {sh[6:0], 1'b0};
                        end
                    end
                end

                //-------------------------------------------- ACK/NACK maestro
                S_ACKM: begin
                    if (scl_rise)
                        mack <= sda_s[1];                  // 0=ACK, 1=NACK
                    else if (scl_fall) begin
                        if (mack == 1'b0) begin            // ACK -> otro byte
                            sh    <= data_tx;
                            sda_o <= data_tx[7];
                            st    <= S_TX;
                        end else begin                     // NACK -> terminar
                            sda_o <= 1'b1;
                            st    <= S_WAIT;
                        end
                    end
                end

                //-------------------------------------------- espera STOP
                S_WAIT: sda_o <= 1'b1;

                default: st <= S_IDLE;
                endcase
            end
        end
    end

endmodule

I2C/Codigo/i2c_master.v
//==============================================================================
// i2c_master.v
// Maestro I2C implementado con una Maquina de Estados Finitos (FSM)
//
// - Direccion de 7 bits + bit R/W (0 = escritura, 1 = lectura)
// - Genera las condiciones de START y STOP (como en los diagramas:
//   SDA baja/sube mientras SCL esta en alto)
// - Cada bit de SCL se divide en 4 fases:
//     fase 0: SCL=0 -> se coloca el dato en SDA (SDA solo cambia con SCL bajo)
//     fase 1: SCL=1
//     fase 2: SCL=1 -> se muestrea SDA (dato estable durante SCL alto)
//     fase 3: SCL=0
// - Verifica el bit ACK/NACK del esclavo (ack_error = 1 si recibe NACK)
// - En lectura, el maestro responde NACK tras el byte (lectura de 1 byte)
//
// SDA y SCL son de drenador abierto: el modulo solo fuerza '0' o libera
// la linea ('z'); las resistencias de pull-up (externas o tri1 en el
// testbench) la llevan a '1'.
//==============================================================================
module i2c_master #(
    parameter CLK_FREQ = 50_000_000,   // frecuencia del reloj del sistema
    parameter I2C_FREQ = 100_000       // frecuencia de SCL (100 kHz estandar)
)(
    input  wire       clk,
    input  wire       rst_n,
    input  wire       start,       // pulso: inicia una transaccion
    input  wire [6:0] addr,        // direccion de 7 bits del esclavo
    input  wire       rw,          // 0 = escribir, 1 = leer
    input  wire [7:0] data_wr,     // byte a escribir
    output reg  [7:0] data_rd,     // byte leido del esclavo
    output reg        busy,        // transaccion en curso
    output reg        done,        // pulso: transaccion terminada
    output reg        ack_error,   // 1 = el esclavo respondio NACK
    inout  wire       sda,
    inout  wire       scl
);

    //-------------------------------------------------------------------------
    // Divisor de reloj: un "tick" por cada cuarto de periodo de SCL
    //-------------------------------------------------------------------------
    localparam integer DIV = CLK_FREQ / (I2C_FREQ * 4);

    reg [15:0] cnt;
    wire tick = (cnt == DIV-1);

    //-------------------------------------------------------------------------
    // Salidas de drenador abierto (1 = liberar linea, 0 = forzar bajo)
    //-------------------------------------------------------------------------
    reg sda_o, scl_o;
    assign sda = sda_o ? 1'bz : 1'b0;
    assign scl = scl_o ? 1'bz : 1'b0;

    //-------------------------------------------------------------------------
    // Estados de la FSM
    //-------------------------------------------------------------------------
    localparam [3:0] ST_IDLE  = 4'd0,   // reposo (SDA=SCL=1)
                     ST_START = 4'd1,   // condicion de START
                     ST_ADDR  = 4'd2,   // envia direccion (7 bits) + R/W
                     ST_ACKA  = 4'd3,   // lee ACK/NACK de la direccion
                     ST_WR    = 4'd4,   // envia byte de datos
                     ST_ACKW  = 4'd5,   // lee ACK/NACK del dato
                     ST_RD    = 4'd6,   // recibe byte de datos
                     ST_MACK  = 4'd7,   // maestro envia NACK (fin de lectura)
                     ST_STOP  = 4'd8;   // condicion de STOP

    reg [3:0] state;
    reg [1:0] phase;      // fase dentro del bit (0..3)
    reg [3:0] bit_cnt;    // contador de bits
    reg [7:0] shifter;    // registro de desplazamiento
    reg       rw_r;       // R/W registrado
    reg       nack;       // ACK muestreado (1 = NACK)

    always @(posedge clk or negedge rst_n) begin
        if (!rst_n)
            cnt <= 0;
        else if (state == ST_IDLE || tick)
            cnt <= 0;
        else
            cnt <= cnt + 1'b1;
    end

    always @(posedge clk or negedge rst_n) begin
        if (!rst_n) begin
            state     <= ST_IDLE;
            sda_o     <= 1'b1;
            scl_o     <= 1'b1;
            busy      <= 1'b0;
            done      <= 1'b0;
            ack_error <= 1'b0;
            phase     <= 2'd0;
            bit_cnt   <= 4'd0;
            data_rd   <= 8'h00;
            shifter   <= 8'h00;
            rw_r      <= 1'b0;
            nack      <= 1'b0;
        end else begin
            done <= 1'b0;                       // 'done' es un pulso de 1 ciclo

            case (state)
            //------------------------------------------------ reposo
            ST_IDLE: begin
                sda_o <= 1'b1;
                scl_o <= 1'b1;
                phase <= 2'd0;
                if (start) begin
                    busy      <= 1'b1;
                    ack_error <= 1'b0;
                    shifter   <= {addr, rw};    // direccion + bit R/W
                    rw_r      <= rw;
                    state     <= ST_START;
                end
            end

            //------------------------------------------------ START:
            // SDA cae mientras SCL permanece en alto
            ST_START: if (tick) begin
                phase <= phase + 1'b1;
                case (phase)
                    2'd0: begin sda_o <= 1'b1; scl_o <= 1'b1; end
                    2'd1: sda_o <= 1'b0;                    // <- START
                    2'd2: ;
                    2'd3: begin
                        scl_o   <= 1'b0;
                        bit_cnt <= 4'd0;
                        state   <= ST_ADDR;
                    end
                endcase
            end

            //------------------------------------------------ direccion + R/W
            ST_ADDR: if (tick) begin
                phase <= phase + 1'b1;
                case (phase)
                    2'd0: sda_o <= shifter[7];  // coloca bit con SCL bajo
                    2'd1: scl_o <= 1'b1;
                    2'd2: ;                     // dato estable con SCL alto
                    2'd3: begin
                        scl_o   <= 1'b0;
                        shifter <= {shifter[6:0], 1'b0};
                        if (bit_cnt == 4'd7) begin
                            bit_cnt <= 4'd0;
                            state   <= ST_ACKA;
                        end else
                            bit_cnt <= bit_cnt + 1'b1;
                    end
                endcase
            end

            //------------------------------------------------ ACK de direccion
            // El maestro libera SDA; el esclavo debe llevarla a 0 (ACK)
            ST_ACKA: if (tick) begin
                phase <= phase + 1'b1;
                case (phase)
                    2'd0: sda_o <= 1'b1;        // libera SDA
                    2'd1: scl_o <= 1'b1;
                    2'd2: nack  <= sda;         // muestrea ACK/NACK
                    2'd3: begin
                        scl_o <= 1'b0;
                        if (nack) begin
                            ack_error <= 1'b1;  // nadie respondio -> STOP
                            state     <= ST_STOP;
                        end else if (rw_r)
                            state <= ST_RD;
                        else begin
                            shifter <= data_wr;
                            state   <= ST_WR;
                        end
                    end
                endcase
            end

            //------------------------------------------------ escritura de byte
            ST_WR: if (tick) begin
                phase <= phase + 1'b1;
                case (phase)
                    2'd0: sda_o <= shifter[7];
                    2'd1: scl_o <= 1'b1;
                    2'd2: ;
                    2'd3: begin
                        scl_o   <= 1'b0;
                        shifter <= {shifter[6:0], 1'b0};
                        if (bit_cnt == 4'd7) begin
                            bit_cnt <= 4'd0;
                            state   <= ST_ACKW;
                        end else
                            bit_cnt <= bit_cnt + 1'b1;
                    end
                endcase
            end

            //------------------------------------------------ ACK del dato
            ST_ACKW: if (tick) begin
                phase <= phase + 1'b1;
                case (phase)
                    2'd0: sda_o <= 1'b1;
                    2'd1: scl_o <= 1'b1;
                    2'd2: nack  <= sda;
                    2'd3: begin
                        scl_o <= 1'b0;
                        if (nack) ack_error <= 1'b1;
                        state <= ST_STOP;       // 1 byte por transaccion
                    end
                endcase
            end

            //------------------------------------------------ lectura de byte
            // El maestro libera SDA y muestrea; el esclavo transmite
            ST_RD: if (tick) begin
                phase <= phase + 1'b1;
                case (phase)
                    2'd0: sda_o <= 1'b1;                     // SDA liberada
                    2'd1: scl_o <= 1'b1;
                    2'd2: shifter <= {shifter[6:0], sda};    // muestrea bit
                    2'd3: begin
                        scl_o <= 1'b0;
                        if (bit_cnt == 4'd7) begin
                            bit_cnt <= 4'd0;
                            data_rd <= shifter;
                            state   <= ST_MACK;
                        end else
                            bit_cnt <= bit_cnt + 1'b1;
                    end
                endcase
            end

            //------------------------------------------------ NACK del maestro
            // Tras el ultimo byte leido, el maestro deja SDA en alto (NACK)
            ST_MACK: if (tick) begin
                phase <= phase + 1'b1;
                case (phase)
                    2'd0: sda_o <= 1'b1;        // NACK (fin de la lectura)
                    2'd1: scl_o <= 1'b1;
                    2'd2: ;
                    2'd3: begin
                        scl_o <= 1'b0;
                        state <= ST_STOP;
                    end
                endcase
            end

            //------------------------------------------------ STOP:
            // SDA sube mientras SCL esta en alto
            ST_STOP: if (tick) begin
                phase <= phase + 1'b1;
                case (phase)
                    2'd0: begin sda_o <= 1'b0; scl_o <= 1'b0; end
                    2'd1: scl_o <= 1'b1;
                    2'd2: sda_o <= 1'b1;        // <- STOP
                    2'd3: begin
                        busy  <= 1'b0;
                        done  <= 1'b1;
                        state <= ST_IDLE;
                    end
                endcase
            end

            default: state <= ST_IDLE;
            endcase
        end
    end

endmodule

I2C/Codigo/tb_i2c.v
//==============================================================================
// tb_i2c.v
// Testbench: conecta i2c_master <-> i2c_slave por el bus (SDA, SCL)
//
// Escenario simulado (igual a los diagramas):
//   1) ESCRITURA : START + direccion 1100100 + W(0) + ACK + byte 0xA5 + ACK + STOP
//   2) LECTURA   : START + direccion 1100100 + R(1) + ACK + el esclavo devuelve
//                  el byte que recibio + NACK del maestro + STOP
//   3) Direccion equivocada: el esclavo no responde -> NACK (ack_error = 1)
//
// Las lineas SDA y SCL se declaran 'tri1' para modelar las resistencias
// de pull-up del bus I2C (valen '1' cuando nadie las fuerza a '0').
//==============================================================================
`timescale 1ns/1ps

module tb_i2c;

    // Reloj de 50 MHz y reset
    reg clk = 1'b0;
    reg rst_n = 1'b0;
    always #10 clk = ~clk;                 // periodo 20 ns

    // Bus I2C con pull-ups
    tri1 sda;
    tri1 scl;

    // Interfaz del maestro
    reg         start = 1'b0;
    reg  [6:0]  addr;
    reg         rw;
    reg  [7:0]  data_wr;
    wire [7:0]  data_rd;
    wire        busy, done, ack_error;

    // Interfaz del esclavo
    wire [7:0] data_rx;
    wire       rx_valid;
    reg  [7:0] slave_mem = 8'h00;          // "memoria" de 1 byte del esclavo

    // El esclavo devuelve en lectura lo ultimo que se le escribio
    always @(posedge clk)
        if (rx_valid) slave_mem <= data_rx;

    //-------------------------------------------------------------------------
    // DUTs  (I2C a 1 MHz para acortar la simulacion; usar 100_000 en HW real)
    //-------------------------------------------------------------------------
    i2c_master #(
        .CLK_FREQ(50_000_000),
        .I2C_FREQ(1_000_000)
    ) u_master (
        .clk(clk), .rst_n(rst_n),
        .start(start), .addr(addr), .rw(rw),
        .data_wr(data_wr), .data_rd(data_rd),
        .busy(busy), .done(done), .ack_error(ack_error),
        .sda(sda), .scl(scl)
    );

    i2c_slave #(
        .ADDR(7'b1100100)                  // 0x64, como en el diagrama
    ) u_slave (
        .clk(clk), .rst_n(rst_n),
        .scl(scl), .sda(sda),
        .data_tx(slave_mem),
        .data_rx(data_rx), .rx_valid(rx_valid)
    );

    //-------------------------------------------------------------------------
    // Tarea: lanzar una transaccion y esperar a que termine
    //-------------------------------------------------------------------------
    task transaccion(input [6:0] a, input r, input [7:0] d);
        begin
            @(posedge clk);
            addr    <= a;
            rw      <= r;
            data_wr <= d;
            start   <= 1'b1;
            @(posedge clk);
            start   <= 1'b0;
            wait (done);
            @(posedge clk);
        end
    endtask

    integer errores = 0;

    initial begin
        $dumpfile("i2c_sim.vcd");
        $dumpvars(0, tb_i2c);

        // Reset
        repeat (5) @(posedge clk);
        rst_n = 1'b1;
        repeat (5) @(posedge clk);

        //---------------- 1) ESCRITURA: maestro -> esclavo (0xA5) ----------------
        $display("\n[%0t ns] ESCRITURA: addr=0x64, dato=0xA5", $time);
        transaccion(7'b1100100, 1'b0, 8'hA5);
        $display("[%0t ns]   esclavo recibio  = 0x%02h  | ack_error=%b",
                  $time, data_rx, ack_error);
        if (data_rx !== 8'hA5 || ack_error) begin
            $display("   >>> ERROR en la escritura"); errores = errores + 1;
        end

        //---------------- 2) LECTURA: esclavo -> maestro --------------------------
        $display("\n[%0t ns] LECTURA:   addr=0x64", $time);
        transaccion(7'b1100100, 1'b1, 8'h00);
        $display("[%0t ns]   maestro leyo     = 0x%02h  | ack_error=%b",
                  $time, data_rd, ack_error);
        if (data_rd !== 8'hA5 || ack_error) begin
            $display("   >>> ERROR en la lectura"); errores = errores + 1;
        end

        //---------------- 3) Direccion inexistente -> NACK ------------------------
        $display("\n[%0t ns] ESCRITURA a direccion inexistente 0x23", $time);
        transaccion(7'h23, 1'b0, 8'hFF);
        $display("[%0t ns]   ack_error=%b (se espera 1 = NACK)", $time, ack_error);
        if (!ack_error) begin
            $display("   >>> ERROR: se esperaba NACK"); errores = errores + 1;
        end

        //---------------- Resumen --------------------------------------------------
        if (errores == 0)
            $display("\n=== SIMULACION EXITOSA: todas las pruebas pasaron ===\n");
        else
            $display("\n=== SIMULACION CON %0d ERROR(ES) ===\n", errores);

        $finish;
    end

    // Guardia de tiempo maximo
    initial begin
        #2_000_000;   // 2 ms
        $display(">>> TIMEOUT de simulacion");
        $finish;
    end

endmodule

I2C/Codigo/i2c_sim.vcd
$date
	Thu Jul 16 16:33:45 2026
$end
$version
	Icarus Verilog
$end
$timescale
	1ps
$end
$scope module tb_i2c $end
$var wire 1 ! scl $end
$var wire 1 " sda $end
$var wire 1 # rx_valid $end
$var wire 1 $ done $end
$var wire 8 % data_rx [7:0] $end
$var wire 8 & data_rd [7:0] $end
$var wire 1 ' busy $end
$var wire 1 ( ack_error $end
$var reg 7 ) addr [6:0] $end
$var reg 1 * clk $end
$var reg 8 + data_wr [7:0] $end
$var reg 1 , rst_n $end
$var reg 1 - rw $end
$var reg 8 . slave_mem [7:0] $end
$var reg 1 / start $end
$var integer 32 0 errores [31:0] $end
$scope module u_master $end
$var wire 7 1 addr [6:0] $end
$var wire 1 * clk $end
$var wire 8 2 data_wr [7:0] $end
$var wire 1 , rst_n $end
$var wire 1 - rw $end
$var wire 1 ! scl $end
$var wire 1 " sda $end
$var wire 1 / start $end
$var wire 1 3 tick $end
$var parameter 32 4 CLK_FREQ $end
$var parameter 32 5 DIV $end
$var parameter 32 6 I2C_FREQ $end
$var parameter 4 7 ST_ACKA $end
$var parameter 4 8 ST_ACKW $end
$var parameter 4 9 ST_ADDR $end
$var parameter 4 : ST_IDLE $end
$var parameter 4 ; ST_MACK $end
$var parameter 4 < ST_RD $end
$var parameter 4 = ST_START $end
$var parameter 4 > ST_STOP $end
$var parameter 4 ? ST_WR $end
$var reg 1 ( ack_error $end
$var reg 4 @ bit_cnt [3:0] $end
$var reg 1 ' busy $end
$var reg 16 A cnt [15:0] $end
$var reg 8 B data_rd [7:0] $end
$var reg 1 $ done $end
$var reg 1 C nack $end
$var reg 2 D phase [1:0] $end
$var reg 1 E rw_r $end
$var reg 1 F scl_o $end
$var reg 1 G sda_o $end
$var reg 8 H shifter [7:0] $end
$var reg 4 I state [3:0] $end
$upscope $end
$scope module u_slave $end
$var wire 1 * clk $end
$var wire 8 J data_tx [7:0] $end
$var wire 1 , rst_n $end
$var wire 1 ! scl $end
$var wire 1 " sda $end
$var wire 1 K start_c $end
$var wire 1 L stop_c $end
$var wire 1 M scl_rise $end
$var wire 1 N scl_fall $end
$var parameter 7 O ADDR $end
$var parameter 3 P S_ACKA $end
$var parameter 3 Q S_ACKM $end
$var parameter 3 R S_ACKR $end
$var parameter 3 S S_ADDR $end
$var parameter 3 T S_IDLE $end
$var parameter 3 U S_RX $end
$var parameter 3 V S_TX $end
$var parameter 3 W S_WAIT $end
$var reg 4 X bit_cnt [3:0] $end
$var reg 8 Y data_rx [7:0] $end
$var reg 1 Z mack $end
$var reg 1 [ rw $end
$var reg 1 # rx_valid $end
$var reg 3 \ scl_s [2:0] $end
$var reg 1 ] sda_o $end
$var reg 3 ^ sda_s [2:0] $end
$var reg 8 _ sh [7:0] $end
$var reg 3 ` st [2:0] $end
$upscope $end
$scope task transaccion $end
$var reg 7 a a [6:0] $end
$var reg 8 b d [7:0] $end
$var reg 1 c r $end
$upscope $end
$upscope $end
$enddefinitions $end
$comment Show the parameter values. $end
$dumpall
b111 W
b101 V
b11 U
b0 T
b1 S
b100 R
b110 Q
b10 P
b1100100 O
b100 ?
b1000 >
b1 =
b110 <
b111 ;
b0 :
b10 9
b101 8
b11 7
b11110100001001000000 6
b1100 5
b10111110101111000010000000 4
$end
#0
$dumpvars
xc
bx b
bx a
bx `
bx _
bx ^
x]
bx \
x[
xZ
bx Y
bx X
xN
xM
xL
xK
b0 J
bx I
bx H
xG
xF
xE
bx D
xC
bx B
bx A
bx @
x3
bx 2
bx 1
b0 0
0/
b0 .
x-
0,
bx +
0*
bx )
x(
x'
bx &
bx %
x$
x#
x"
x!
$end
#10000
0L
0K
1!
1"
0M
0N
03
b0 A
0C
0E
b0 H
b0 &
b0 B
b0 @
b0 D
0(
0$
0'
1F
1G
b0 I
b111 ^
b111 \
0#
b0 %
b0 Y
1Z
0[
b0 _
b0 X
1]
b0 `
1*
#20000
0*
#30000
1*
#40000
0*
#50000
1*
#60000
0*
#70000
1*
#80000
0*
#90000
1,
1*
#100000
0*
#110000
1*
#120000
0*
#130000
1*
#140000
0*
#150000
1*
#160000
0*
#170000
1*
#180000
0*
#190000
b10100101 b
0c
b1100100 a
1*
#200000
0*
#210000
1/
b10100101 +
b10100101 2
0-
b1100100 )
b1100100 1
1*
#220000
0*
#230000
b1 I
b11001000 H
1'
0/
1*
#240000
0*
#250000
b1 A
1*
#260000
0*
#270000
b10 A
1*
#280000
0*
#290000
b11 A
1*
#300000
0*
#310000
b100 A
1*
#320000
0*
#330000
b101 A
1*
#340000
0*
#350000
b110 A
1*
#360000
0*
#370000
b111 A
1*
#380000
0*
#390000
b1000 A
1*
#400000
0*
#410000
b1001 A
1*
#420000
0*
#430000
b1010 A
1*
#440000
0*
#450000
13
b1011 A
1*
#460000
0*
#470000
b1 D
03
b0 A
1*
#480000
0*
#490000
b1 A
1*
#500000
0*
#510000
b10 A
1*
#520000
0*
#530000
b11 A
1*
#540000
0*
#550000
b100 A
1*
#560000
0*
#570000
b101 A
1*
#580000
0*
#590000
b110 A
1*
#600000
0*
#610000
b111 A
1*
#620000
0*
#630000
b1000 A
1*
#640000
0*
#650000
b1001 A
1*
#660000
0*
#670000
b1010 A
1*
#680000
0*
#690000
13
b1011 A
1*
#700000
0*
#710000
0"
0G
b10 D
03
b0 A
1*
#720000
0*
#730000
b1 A
b110 ^
1*
#740000
0*
#750000
1K
b100 ^
b10 A
1*
#760000
0*
#770000
0K
b11 A
b0 ^
b1 `
1*
#780000
0*
#790000
b100 A
1*
#800000
0*
#810000
b101 A
1*
#820000
0*
#830000
b110 A
1*
#840000
0*
#850000
b111 A
1*
#860000
0*
#870000
b1000 A
1*
#880000
0*
#890000
b1001 A
1*
#900000
0*
#910000
b1010 A
1*
#920000
0*
#930000
13
b1011 A
1*
#940000
0*
#950000
b11 D
03
b0 A
1*
#960000
0*
#970000
b1 A
1*
#980000
0*
#990000
b10 A
1*
#1000000
0*
#1010000
b11 A
1*
#1020000
0*
#1030000
b100 A
1*
#1040000
0*
#1050000
b101 A
1*
#1060000
0*
#1070000
b110 A
1*
#1080000
0*
#1090000
b111 A
1*
#1100000
0*
#1110000
b1000 A
1*
#1120000
0*
#1130000
b1001 A
1*
#1140000
0*
#1150000
b1010 A
1*
#1160000
0*
#1170000
13
b1011 A
1*
#1180000
0*
#1190000
0!
b10 I
0F
b0 D
03
b0 A
1*
#1200000
0*
#1210000
b1 A
b110 \
1*
#1220000
0*
#1230000
1N
b100 \
b10 A
1*
#1240000
0*
#1250000
0N
b11 A
b0 \
1*
#1260000
0*
#1270000
b100 A
1*
#1280000
0*
#1290000
b101 A
1*
#1300000
0*
#1310000
b110 A
1*
#1320000
0*
#1330000
b111 A
1*
#1340000
0*
#1350000
b1000 A
1*
#1360000
0*
#1370000
b1001 A
1*
#1380000
0*
#1390000
b1010 A
1*
#1400000
0*
#1410000
13
b1011 A
1*
#1420000
0*
#1430000
1"
1G
b1 D
03
b0 A
1*
#1440000
0*
#1450000
b1 A
b1 ^
1*
#1460000
0*
#1470000
b11 ^
b10 A
1*
#1480000
0*
#1490000
b11 A
b111 ^
1*
#1500000
0*
#1510000
b100 A
1*
#1520000
0*
#1530000
b101 A
1*
#1540000
0*
#1550000
b110 A
1*
#1560000
0*
#1570000
b111 A
1*
#1580000
0*
#1590000
b1000 A
1*
#1600000
0*
#1610000
b1001 A
1*
#1620000
0*
#1630000
b1010 A
1*
#1640000
0*
#1650000
13
b1011 A
1*
#1660000
0*
#1670000
1!
1F
b10 D
03
b0 A
1*
#1680000
0*
#1690000
b1 A
b1 \
1*
#1700000
0*
#1710000
1M
b11 \
b10 A
1*
#1720000
0*
#1730000
0M
b11 A
b111 \
b1 X
b1 _
1*
#1740000
0*
#1750000
b100 A
1*
#1760000
0*
#1770000
b101 A
1*
#1780000
0*
#1790000
b110 A
1*
#1800000
0*
#1810000
b111 A
1*
#1820000
0*
#1830000
b1000 A
1*
#1840000
0*
#1850000
b1001 A
1*
#1860000
0*
#1870000
b1010 A
1*
#1880000
0*
#1890000
13
b1011 A
1*
#1900000
0*
#1910000
b11 D
03
b0 A
1*
#1920000
0*
#1930000
b1 A
1*
#1940000
0*
#1950000
b10 A
1*
#1960000
0*
#1970000
b11 A
1*
#1980000
0*
#1990000
b100 A
1*
#2000000
0*
#2010000
b101 A
1*
#2020000
0*
#2030000
b110 A
1*
#2040000
0*
#2050000
b111 A
1*
#2060000
0*
#2070000
b1000 A
1*
#2080000
0*
#2090000
b1001 A
1*
#2100000
0*
#2110000
b1010 A
1*
#2120000
0*
#2130000
13
b1011 A
1*
#2140000
0*
#2150000
0!
b1 @
b10010000 H
0F
b0 D
03
b0 A
1*
#2160000
0*
#2170000
b1 A
b110 \
1*
#2180000
0*
#2190000
1N
b100 \
b10 A
1*
#2200000
0*
#2210000
0N
b11 A
b0 \
1*
#2220000
0*
#2230000
b100 A
1*
#2240000
0*
#2250000
b101 A
1*
#2260000
0*
#2270000
b110 A
1*
#2280000
0*
#2290000
b111 A
1*
#2300000
0*
#2310000
b1000 A
1*
#2320000
0*
#2330000
b1001 A
1*
#2340000
0*
#2350000
b1010 A
1*
#2360000
0*
#2370000
13
b1011 A
1*
#2380000
0*
#2390000
b1 D
03
b0 A
1*
#2400000
0*
#2410000
b1 A
1*
#2420000
0*
#2430000
b10 A
1*
#2440000
0*
#2450000
b11 A
1*
#2460000
0*
#2470000
b100 A
1*
#2480000
0*
#2490000
b101 A
1*
#2500000
0*
#2510000
b110 A
1*
#2520000
0*
#2530000
b111 A
1*
#2540000
0*
#2550000
b1000 A
1*
#2560000
0*
#2570000
b1001 A
1*
#2580000
0*
#2590000
b1010 A
1*
#2600000
0*
#2610000
13
b1011 A
1*
#2620000
0*
#2630000
1!
1F
b10 D
03
b0 A
1*
#2640000
0*
#2650000
b1 A
b1 \
1*
#2660000
0*
#2670000
1M
b11 \
b10 A
1*
#2680000
0*
#2690000
0M
b11 A
b111 \
b10 X
b11 _
1*
#2700000
0*
#2710000
b100 A
1*
#2720000
0*
#2730000
b101 A
1*
#2740000
0*
#2750000
b110 A
1*
#2760000
0*
#2770000
b111 A
1*
#2780000
0*
#2790000
b1000 A
1*
#2800000
0*
#2810000
b1001 A
1*
#2820000
0*
#2830000
b1010 A
1*
#2840000
0*
#2850000
13
b1011 A
1*
#2860000
0*
#2870000
b11 D
03
b0 A
1*
#2880000
0*
#2890000
b1 A
1*
#2900000
0*
#2910000
b10 A
1*
#2920000
0*
#2930000
b11 A
1*
#2940000
0*
#2950000
b100 A
1*
#2960000
0*
#2970000
b101 A
1*
#2980000
0*
#2990000
b110 A
1*
#3000000
0*
#3010000
b111 A
1*
#3020000
0*
#3030000
b1000 A
1*
#3040000
0*
#3050000
b1001 A
1*
#3060000
0*
#3070000
b1010 A
1*
#3080000
0*
#3090000
13
b1011 A
1*
#3100000
0*
#3110000
0!
b10 @
b100000 H
0F
b0 D
03
b0 A
1*
#3120000
0*
#3130000
b1 A
b110 \
1*
#3140000
0*
#3150000
1N
b100 \
b10 A
1*
#3160000
0*
#3170000
0N
b11 A
b0 \
1*
#3180000
0*
#3190000
b100 A
1*
#3200000
0*
#3210000
b101 A
1*
#3220000
0*
#3230000
b110 A
1*
#3240000
0*
#3250000
b111 A
1*
#3260000
0*
#3270000
b1000 A
1*
#3280000
0*
#3290000
b1001 A
1*
#3300000
0*
#3310000
b1010 A
1*
#3320000
0*
#3330000
13
b1011 A
1*
#3340000
0*
#3350000
0"
0G
b1 D
03
b0 A
1*
#3360000
0*
#3370000
b1 A
b110 ^
1*
#3380000
0*
#3390000
b100 ^
b10 A
1*
#3400000
0*
#3410000
b11 A
b0 ^
1*
#3420000
0*
