Litex_calculadora/divisor/control_div.v
module control_div( clk , rst , init , z0 , last , done , error , load , shift , setq , errset );

 input clk;
 input rst;
 input init;
 input z0;
 input last;

 output reg done;
 output reg error;
 output reg load;
 output reg shift;
 output reg setq;
 output reg errset;

 parameter START  = 3'b000;
 parameter LOAD   = 3'b001;
 parameter ZCHECK = 3'b010;
 parameter SHIFT  = 3'b011;
 parameter SETQ   = 3'b100;
 parameter END    = 3'b101;
 parameter ERR    = 3'b110;

 reg [2:0] state;

 initial begin
  done   = 0;
  error  = 0;
  load   = 0;
  shift  = 0;
  setq   = 0;
  errset = 0;
  state  = 0;
 end

always @(posedge clk) begin
    if (rst) begin
      state = START;
    end else begin
    case(state)

      START:begin
        if(init)
          state = LOAD;
        else
          state = START;
      end

     LOAD: begin
        state = ZCHECK;
     end

     ZCHECK: begin
        if(z0)
          state = ERR;
        else
          state = SHIFT;
     end

     SHIFT: begin
        state = SETQ;
     end

     SETQ: begin
        if(last)
          state = END;
        else
          state = SHIFT;
     end

     END:begin
        if(init)
          state = START;
        else
          state = END;
     end

     ERR:begin
        if(init)
          state = START;
        else
          state = ERR;
     end

     default: state = START;
   endcase
  end
end


always@(*) begin
    case(state)

      START:begin
        done   = 0;
        error  = 0;
        load   = 0;
        shift  = 0;
        setq   = 0;
        errset = 0;
      end

     LOAD: begin
        done   = 0;
        error  = 0;
        load   = 1;
        shift  = 0;
        setq   = 0;
        errset = 0;
     end

     ZCHECK: begin
        done   = 0;
        error  = 0;
        load   = 0;
        shift  = 0;
        setq   = 0;
        errset = 0;
     end

     SHIFT: begin
        done   = 0;
        error  = 0;
        load   = 0;
        shift  = 1;
        setq   = 0;
        errset = 0;
     end

     SETQ: begin
        done   = 0;
        error  = 0;
        load   = 0;
        shift  = 0;
        setq   = 1;
        errset = 0;
     end

     END:begin
        done   = 1;
        error  = 0;
        load   = 0;
        shift  = 0;
        setq   = 0;
        errset = 0;
     end

     ERR:begin
        done   = 1;
        error  = 1;
        load   = 0;
        shift  = 0;
        setq   = 0;
        errset = 1;
     end

     default: begin
        done   = 0;
        error  = 0;
        load   = 1;
        shift  = 0;
        setq   = 0;
        errset = 0;
     end
   endcase
end

`ifdef BENCH
reg [8*40:1] state_name;
always @(*) begin
  case(state)
    START    : state_name = "START";
    LOAD     : state_name = "LOAD";
    ZCHECK   : state_name = "ZCHECK";
    SHIFT    : state_name = "SHIFT";
    SETQ     : state_name = "SETQ";
    END      : state_name = "END";
    ERR      : state_name = "ERR";
  endcase
end
`endif

endmodule

Litex_calculadora/divisor/reg_aq.v
module reg_aq (clk, A, load, shift, setq, neg, diff, errset, aq);
  input clk;
  input [15:0]A;
  input load;
  input shift;
  input setq;
  input neg;
  input [15:0]diff;
  input errset;
  output reg [31:0]aq;

  initial aq = 32'h0;

  always @(negedge clk)
    if(errset)
      aq = {A, 16'hFFFF};
    else if(load)
      aq = {16'h0000, A};
    else if(shift)
      aq = aq << 1;
    else if(setq) begin
      if(neg)
        aq[0] = 1'b0;
      else begin
        aq[31:16] = diff;
        aq[0]     = 1'b1;
      end
    end
    else
      aq = aq;

endmodule

Litex_calculadora/divisor/count_div.v
module count_div (clk, load, inc, last);
  input clk;
  input load;
  input inc;
  output last;
  reg [4:0]cnt;

  initial cnt = 5'h0;

  always @(negedge clk)
    if(load) cnt = 5'h0;
    else if(inc) cnt = cnt + 5'h1;
    else cnt = cnt;

  // 16 shift/subtract iterations are needed for a 16-bit division; `last`
  // is sampled by control_div *after* the counter's post-iteration
  // increment, so the threshold is 16 (not 15) to avoid stopping one
  // iteration early.
  assign last = (cnt == 5'd16);

endmodule

Litex_calculadora/divisor/sub_div.v
module sub_div (R, B, diff, neg);
  input  [15:0]R;
  input  [15:0]B;
  output [15:0]diff;
  output neg;

  wire [16:0] result;

  assign result = {1'b0, R} - {1'b0, B};
  assign diff   = result[15:0];
  assign neg    = result[16];

endmodule

Litex_calculadora/divisor/comp_div0.v
module comp_div0(B, z);
  input [15:0]B;
  output z;
  reg tmp;

  initial tmp = 0;
  assign z = tmp;

    always@(*)
      tmp = (B==0) ? 1'b1 : 1'b0;

endmodule

Litex_calculadora/divisor/div_32.v
module div_32(clk , rst , init , A , B , quotient , remainder , done , error);

  input rst;
  input clk;
  input init;
  input [15:0] A;
  input [15:0] B;
  output [15:0] quotient;
  output [15:0] remainder;
  output done;
  output error;

  wire w_load;
  wire w_shift;
  wire w_setq;
  wire w_errset;
  wire w_z0;
  wire w_last;
  wire w_neg;

  wire [15:0] w_diff;
  wire [31:0] w_aq;

  comp_div0 comp0  (.B(B), .z(w_z0));
  sub_div   sub0   (.R(w_aq[31:16]), .B(B), .diff(w_diff), .neg(w_neg));
  count_div count0 (.clk(clk), .load(w_load), .inc(w_setq), .last(w_last));
  reg_aq    aq0    (.clk(clk), .A(A), .load(w_load), .shift(w_shift), .setq(w_setq), .neg(w_neg), .diff(w_diff), .errset(w_errset), .aq(w_aq));
  control_div control0 (.clk(clk), .rst(rst), .init(init), .z0(w_z0), .last(w_last),
    .done(done), .error(error), .load(w_load), .shift(w_shift), .setq(w_setq), .errset(w_errset));

  assign remainder = w_aq[31:16];
  assign quotient  = w_aq[15:0];

endmodule

Litex_calculadora/divisor/div_32_TB.v
`timescale 1ns / 1ps
`define SIMULATION
module div_32_TB;
   reg  clk;
   reg  rst;
   reg  start;
   reg  [15:0]A;
   reg  [15:0]B;
   wire [15:0] quotient;
   wire [15:0] remainder;
   wire done;
   wire error;
   div_32 uut (.clk(clk) , .rst(rst) , .init(start) , .A(A) , .B(B) , .quotient(quotient) , .remainder(remainder) , .done(done) , .error(error));
   parameter PERIOD          = 20;
   parameter real DUTY_CYCLE = 0.5;
   parameter OFFSET          = 0;
   reg [20:0] i;
	event reset_trigger;
	event reset_done_trigger;
	initial begin
	  forever begin
	   @ (reset_trigger);
		@ (negedge clk);
		rst = 1;
		@ (negedge clk);
		rst = 0;
		-> reset_done_trigger;
		end
	end
   initial begin  // Initialize Inputs
      clk = 0; rst = 1; start = 0; A = 16'h000A; B = 16'h0003; // 10 / 3 = 3 remainder 1
   end
   initial  begin  // Process for clk
     #OFFSET;
     forever
       begin
         clk = 1'b0;
         #(PERIOD-(PERIOD*DUTY_CYCLE)) clk = 1'b1;
         #(PERIOD*DUTY_CYCLE);
       end
   end
   initial begin // Reset the system, start the division
        #10 -> reset_trigger;
        @ (reset_done_trigger);
        @ (posedge clk);
        start = 0;
        @ (posedge clk);
        start = 1;
       for(i=0; i<2; i=i+1) begin
         @ (posedge clk);
       end
          start = 0;
       for(i=0; i<40; i=i+1) begin
         @ (posedge clk);
       end
   end
   initial begin: TEST_CASE
     $dumpfile("div_32_TB.vcd");
     $dumpvars(-1, uut);
     #((PERIOD*DUTY_CYCLE)*160) $finish;
   end
endmodule

Litex_calculadora/divisor/div_32_TB.vcd
$date
	Thu Jul 16 11:20:31 2026
$end
$version
	Icarus Verilog
$end
$timescale
	1ps
$end
$scope module div_32_TB $end
$scope module uut $end
$var wire 16 ! A [15:0] $end
$var wire 16 " B [15:0] $end
$var wire 1 # clk $end
$var wire 1 $ init $end
$var wire 1 % rst $end
$var wire 1 & w_z0 $end
$var wire 1 ' w_shift $end
$var wire 1 ( w_setq $end
$var wire 1 ) w_neg $end
$var wire 1 * w_load $end
$var wire 1 + w_last $end
$var wire 1 , w_errset $end
$var wire 16 - w_diff [15:0] $end
$var wire 32 . w_aq [31:0] $end
$var wire 16 / remainder [15:0] $end
$var wire 16 0 quotient [15:0] $end
$var wire 1 1 error $end
$var wire 1 2 done $end
$scope module aq0 $end
$var wire 16 3 A [15:0] $end
$var wire 1 # clk $end
$var wire 1 ' shift $end
$var wire 1 ( setq $end
$var wire 1 ) neg $end
$var wire 1 * load $end
$var wire 1 , errset $end
$var wire 16 4 diff [15:0] $end
$var reg 32 5 aq [31:0] $end
$upscope $end
$scope module comp0 $end
$var wire 16 6 B [15:0] $end
$var wire 1 & z $end
$var reg 1 7 tmp $end
$upscope $end
$scope module control0 $end
$var wire 1 # clk $end
$var wire 1 $ init $end
$var wire 1 % rst $end
$var wire 1 & z0 $end
$var wire 1 + last $end
$var parameter 3 8 END $end
$var parameter 3 9 ERR $end
$var parameter 3 : LOAD $end
$var parameter 3 ; SETQ $end
$var parameter 3 < SHIFT $end
$var parameter 3 = START $end
$var parameter 3 > ZCHECK $end
$var reg 1 2 done $end
$var reg 1 1 error $end
$var reg 1 , errset $end
$var reg 1 * load $end
$var reg 1 ( setq $end
$var reg 1 ' shift $end
$var reg 3 ? state [2:0] $end
$var reg 320 @ state_name [320:1] $end
$upscope $end
$scope module count0 $end
$var wire 1 # clk $end
$var wire 1 ( inc $end
$var wire 1 * load $end
$var wire 1 + last $end
$var reg 5 A cnt [4:0] $end
$upscope $end
$scope module sub0 $end
$var wire 16 B B [15:0] $end
$var wire 16 C R [15:0] $end
$var wire 17 D result [16:0] $end
$var wire 1 ) neg $end
$var wire 16 E diff [15:0] $end
$upscope $end
$upscope $end
$upscope $end
$enddefinitions $end
$comment Show the parameter values. $end
$dumpall
b10 >
b0 =
b11 <
b100 ;
b1 :
b110 9
b101 8
$end
#0
$dumpvars
b1111111111111101 E
b11111111111111101 D
b0 C
b11 B
b0 A
b101001101010100010000010101001001010100 @
b0 ?
07
b11 6
b0 5
b1111111111111101 4
b1010 3
02
01
b0 0
b0 /
b0 .
b1111111111111101 -
0,
0+
0*
1)
0(
0'
0&
1%
0$
0#
b11 "
b1010 !
$end
#10000
1#
#20000
0#
#30000
1#
#40000
0%
0#
#50000
1#
#60000
0#
#70000
1$
1#
#80000
0#
#90000
1*
b1001100010011110100000101000100 @
b1 ?
1#
#100000
b1010 0
b1010 .
b1010 5
0#
#110000
b10110100100001101001000010001010100001101001011 @
0*
0$
b10 ?
1#
#120000
0#
#130000
1'
b101001101001000010010010100011001010100 @
b11 ?
1#
#140000
b10100 0
b10100 .
b10100 5
0#
#150000
b1010011010001010101010001010001 @
1(
0'
b100 ?
1#
#160000
b1 A
0#
#170000
0(
1'
b101001101001000010010010100011001010100 @
b11 ?
1#
#180000
b101000 0
b101000 .
b101000 5
0#
#190000
b1010011010001010101010001010001 @
1(
0'
b100 ?
1#
#200000
b10 A
0#
#210000
0(
1'
b101001101001000010010010100011001010100 @
b11 ?
1#
#220000
b1010000 0
b1010000 .
b1010000 5
0#
#230000
b1010011010001010101010001010001 @
1(
0'
b100 ?
1#
#240000
b11 A
0#
#250000
0(
1'
b101001101001000010010010100011001010100 @
b11 ?
1#
#260000
b10100000 0
b10100000 .
b10100000 5
0#
#270000
b1010011010001010101010001010001 @
1(
0'
b100 ?
1#
#280000
b100 A
0#
#290000
0(
1'
b101001101001000010010010100011001010100 @
b11 ?
1#
#300000
b101000000 0
b101000000 .
b101000000 5
0#
#310000
b1010011010001010101010001010001 @
1(
0'
b100 ?
1#
#320000
b101 A
0#
#330000
0(
1'
b101001101001000010010010100011001010100 @
b11 ?
1#
#340000
b1010000000 0
b1010000000 .
b1010000000 5
0#
#350000
b1010011010001010101010001010001 @
1(
0'
b100 ?
1#
#360000
b110 A
0#
#370000
0(
1'
b101001101001000010010010100011001010100 @
b11 ?
1#
#380000
b10100000000 0
b10100000000 .
b10100000000 5
0#
#390000
b1010011010001010101010001010001 @
1(
0'
b100 ?
1#
#400000
b111 A
0#
#410000
0(
1'
b101001101001000010010010100011001010100 @
b11 ?
1#
#420000
b101000000000 0
b101000000000 .
b101000000000 5
0#
#430000
b1010011010001010101010001010001 @
1(
0'
b100 ?
1#
#440000
b1000 A
0#
#450000
0(
1'
b101001101001000010010010100011001010100 @
b11 ?
1#
#460000
b1010000000000 0
b1010000000000 .
b1010000000000 5
0#
#470000
b1010011010001010101010001010001 @
1(
0'
b100 ?
1#
#480000
b1001 A
0#
#490000
0(
1'
b101001101001000010010010100011001010100 @
b11 ?
1#
#500000
b10100000000000 0
b10100000000000 .
b10100000000000 5
0#
#510000
b1010011010001010101010001010001 @
1(
0'
b100 ?
1#
#520000
b1010 A
0#
#530000
0(
1'
b101001101001000010010010100011001010100 @
b11 ?
1#
#540000
b101000000000000 0
b101000000000000 .
b101000000000000 5
0#
#550000
b1010011010001010101010001010001 @
1(
0'
b100 ?
1#
#560000
b1011 A
0#
#570000
0(
1'
b101001101001000010010010100011001010100 @
b11 ?
1#
#580000
b1010000000000000 0
b1010000000000000 .
b1010000000000000 5
0#
#590000
b1010011010001010101010001010001 @
1(
0'
b100 ?
1#
#600000
b1100 A
0#
#610000
0(
1'
b101001101001000010010010100011001010100 @
b11 ?
1#
#620000
b1111111111111110 -
b1111111111111110 4
b1111111111111110 E
b100000000000000 0
b1 /
b11111111111111110 D
b1 C
b10100000000000000 .
b10100000000000000 5
0#
#630000
b1010011010001010101010001010001 @
1(
0'
b100 ?
1#
#640000
b1101 A
0#
#650000
0(
1'
b101001101001000010010010100011001010100 @
b11 ?
1#
#660000
b1111111111111111 -
b1111111111111111 4
b1111111111111111 E
b1000000000000000 0
b10 /
b11111111111111111 D
b10 C
b101000000000000000 .
b101000000000000000 5
0#
#670000
b1010011010001010101010001010001 @
1(
0'
b100 ?
1#
#680000
b1110 A
0#
#690000
0(
1'
b101001101001000010010010100011001010100 @
b11 ?
1#
#700000
b10 -
b10 4
b10 E
0)
b0 0
b101 /
b10 D
b101 C
b1010000000000000000 .
b1010000000000000000 5
0#
#710000
b1010011010001010101010001010001 @
1(
0'
b100 ?
1#
#720000
b1111111111111111 -
b1111111111111111 4
b1111111111111111 E
1)
b1 0
b10 /
b11111111111111111 D
b10 C
b1111 A
b100000000000000001 .
b100000000000000001 5
0#
#730000
0(
1'
b101001101001000010010010100011001010100 @
b11 ?
1#
#740000
b1 -
b1 4
b1 E
0)
b10 0
b100 /
b1 D
b100 C
b1000000000000000010 .
b1000000000000000010 5
0#
#750000
b1010011010001010101010001010001 @
1(
0'
b100 ?
1#
#760000
b1111111111111110 -
b1111111111111110 4
b1111111111111110 E
1)
b11 0
b1 /
b11111111111111110 D
b1 C
1+
b10000 A
b10000000000000011 .
b10000000000000011 5
0#
#770000
0(
12
b10001010100111001000100 @
b101 ?
1#
