tira_led/ws2812_codigo/rtl/ws2812_timer.v
// ============================================================
// ws2812_timer.v
// Base de tiempos para el protocolo WS2812 (NRZ de un solo hilo)
// Pensado para la Colorlight i9 (reloj de 25 MHz -> 40 ns/ciclo)
//
// Tiempos del WS2812B:
//   Bit '0':  T0H = 0.40 us  |  T0L = 0.85 us
//   Bit '1':  T1H = 0.80 us  |  T1L = 0.45 us
//   Periodo de bit ~= 1.25 us
//   RESET (latch): linea en bajo > 50 us
//
// A 25 MHz:
//   1.25 us = 31.25 ciclos -> usamos 31 (1.24 us, dentro de tolerancia)
//   0.40 us = 10 ciclos
//   0.80 us = 20 ciclos
//   RESET   = 2500 ciclos (100 us, con margen de sobra)
//
// Funcionamiento:
//   - 'run' habilita el conteo del periodo de bit.
//   - 'bit_in' indica que bit se esta transmitiendo (0/1).
//   - 'dout_level' entrega el nivel que debe tener la linea de datos.
//   - 'bit_done' se pulsa 1 ciclo al terminar cada periodo de bit.
//   - 'rst_req' pide generar el tiempo de RESET/latch; 'rst_done'
//     se pulsa 1 ciclo cuando el tiempo de latch termino.
// ============================================================
`timescale 1ns / 1ps

module ws2812_timer #(
    parameter CLK_HZ       = 25_000_000,
    parameter CYCLES_BIT   = 31,    // ~1.25 us
    parameter CYCLES_T0H   = 10,    // ~0.40 us
    parameter CYCLES_T1H   = 20,    // ~0.80 us
    parameter CYCLES_RESET = 2500   // ~100 us
)(
    input  wire clk,
    input  wire rst_n,      // reset asincrono activo en bajo

    input  wire run,        // habilita el conteo de bits
    input  wire bit_in,     // valor del bit a serializar
    input  wire rst_req,    // solicitar periodo de latch (linea en bajo)

    output wire dout_level, // nivel de la linea de datos WS2812
    output wire bit_done,   // pulso: ultimo ciclo de un periodo de bit
    output wire rst_done    // pulso: ultimo ciclo del periodo de latch
);

    // Ancho suficiente para el contador mas grande
    localparam CW = $clog2(CYCLES_RESET + 1);

    reg [CW-1:0] cnt;

    // 'bit_done' y 'rst_done' son COMBINACIONALES: se activan durante
    // el ultimo ciclo del periodo, de modo que la FSM que consume
    // estas senales cambie de estado en el MISMO flanco en que 'cnt'
    // da la vuelta. Asi no aparecen pulsos espurios en la linea al
    // pasar de un pixel al siguiente.
    assign bit_done = run     && (cnt == CYCLES_BIT   - 1);
    assign rst_done = rst_req && (cnt == CYCLES_RESET - 1);

    // ------------------------------------------------------------
    // Contador de periodo de bit / latch
    // ------------------------------------------------------------
    always @(posedge clk or negedge rst_n) begin
        if (!rst_n) begin
            cnt <= {CW{1'b0}};
        end else begin
            if (run) begin
                if (bit_done) cnt <= {CW{1'b0}};
                else          cnt <= cnt + 1'b1;
            end else if (rst_req) begin
                if (rst_done) cnt <= {CW{1'b0}};
                else          cnt <= cnt + 1'b1;
            end else begin
                cnt <= {CW{1'b0}};
            end
        end
    end

    // ------------------------------------------------------------
    // Nivel de salida: alto durante T0H o T1H segun el bit,
    // bajo el resto del periodo. En latch siempre bajo.
    // ------------------------------------------------------------
    wire [CW-1:0] t_high = bit_in ? CYCLES_T1H[CW-1:0] : CYCLES_T0H[CW-1:0];

    assign dout_level = run ? (cnt < t_high) : 1'b0;

endmodule

Proyecto_teclado/Modulos_litex/ws2812_codigo/rtl/ws2812_led.v
// ============================================================
// ws2812_led.v
// Serializador de 24 bits (formato GRB, MSB primero) para UN led
// WS2812. Usa ws2812_timer como base de tiempos.
//
// Protocolo de handshake:
//   - Cuando 'ready' = 1, el modulo puede aceptar un nuevo pixel.
//   - El usuario pone 'data' (24 bits GRB) y pulsa 'valid' 1 ciclo.
//   - El modulo serializa los 24 bits por 'dout'.
//   - Al terminar los 24 bits vuelve a 'ready' = 1 SIN soltar la
//     linea: si se encadenan pixeles seguidos, los bits salen
//     back-to-back (asi se cargan los 64 leds de la matriz).
//   - Si se pulsa 'latch' cuando ready=1, genera el periodo de
//     reset (>50us en bajo) y pulsa 'latch_done'.
//
// Nota de formato: el WS2812 recibe primero G7..G0, luego R7..R0
// y por ultimo B7..B0. Aqui 'data' ya se asume en orden GRB:
//   data[23:16] = G, data[15:8] = R, data[7:0] = B
// ============================================================
`timescale 1ns / 1ps

module ws2812_led #(
    parameter CYCLES_BIT   = 31,
    parameter CYCLES_T0H   = 10,
    parameter CYCLES_T1H   = 20,
    parameter CYCLES_RESET = 2500
)(
    input  wire        clk,
    input  wire        rst_n,

    input  wire [23:0] data,       // pixel GRB
    input  wire        valid,      // pulso: cargar y transmitir 'data'
    input  wire        latch,      // pulso: generar tiempo de reset
    output wire        ready,      // 1 = listo para nuevo pixel/latch
    output reg         latch_done, // pulso: latch terminado

    output wire        dout        // linea de datos hacia la tira/matriz
);

    // ------------------- FSM -------------------
    localparam [1:0] S_IDLE  = 2'd0,
                     S_SHIFT = 2'd1,
                     S_LATCH = 2'd2;

    reg [1:0]  state;
    reg [23:0] shreg;    // registro de desplazamiento (MSB primero)
    reg [4:0]  bit_cnt;  // 0..23

    wire bit_done, rst_done;

    assign ready = (state == S_IDLE);

    // Bit actual = MSB del registro de desplazamiento
    wire cur_bit = shreg[23];

    // ------------------- Timer -------------------
    ws2812_timer #(
        .CYCLES_BIT  (CYCLES_BIT),
        .CYCLES_T0H  (CYCLES_T0H),
        .CYCLES_T1H  (CYCLES_T1H),
        .CYCLES_RESET(CYCLES_RESET)
    ) u_timer (
        .clk       (clk),
        .rst_n     (rst_n),
        .run       (state == S_SHIFT),
        .bit_in    (cur_bit),
        .rst_req   (state == S_LATCH),
        .dout_level(dout),
        .bit_done  (bit_done),
        .rst_done  (rst_done)
    );

    // ------------------- Control -------------------
    always @(posedge clk or negedge rst_n) begin
        if (!rst_n) begin
            state      <= S_IDLE;
            shreg      <= 24'd0;
            bit_cnt    <= 5'd0;
            latch_done <= 1'b0;
        end else begin
            latch_done <= 1'b0;

            case (state)
                S_IDLE: begin
                    if (valid) begin
                        shreg   <= data;
                        bit_cnt <= 5'd0;
                        state   <= S_SHIFT;
                    end else if (latch) begin
                        state <= S_LATCH;
                    end
                end

                S_SHIFT: begin
                    if (bit_done) begin
                        if (bit_cnt == 5'd23) begin
                            state <= S_IDLE;   // pixel completo
                        end else begin
                            shreg   <= {shreg[22:0], 1'b0};
                            bit_cnt <= bit_cnt + 1'b1;
                        end
                    end
                end

                S_LATCH: begin
                    if (rst_done) begin
                        latch_done <= 1'b1;
                        state      <= S_IDLE;
                    end
                end

                default: state <= S_IDLE;
            endcase
        end
    end

endmodule

I2C/ws2812_codigo/rtl/ws2812_matrix8x8.v
// ============================================================
// ws2812_matrix8x8.v
// Controlador del arreglo de 8x8 (64 leds WS2812 en cadena).
//
// - La imagen se carga desde un archivo .hex con $readmemh:
//   64 lineas, cada una un valor de 24 bits en formato GRB
//   (GGRRBB en hexadecimal). La direccion 0 es el primer led
//   de la cadena (esquina segun el cableado de la matriz).
// - El modulo recorre las 64 posiciones, envia cada pixel al
//   serializador ws2812_led y al final genera el latch (>50us).
// - Luego refresca la imagen de forma continua ('frame_done'
//   pulsa 1 ciclo al final de cada cuadro).
// ============================================================
`timescale 1ns / 1ps

module ws2812_matrix8x8 #(
    parameter HEX_FILE     = "image.hex",
    parameter N_LEDS       = 64,
    parameter CYCLES_BIT   = 31,
    parameter CYCLES_T0H   = 10,
    parameter CYCLES_T1H   = 20,
    parameter CYCLES_RESET = 2500
)(
    input  wire clk,
    input  wire rst_n,

    output wire dout,       // hacia el pin DIN de la matriz
    output reg  frame_done  // pulso: cuadro completo enviado
);

    localparam AW = $clog2(N_LEDS);

    // ------------------------------------------------------------
    // Memoria de imagen (se infiere como BRAM en el ECP5)
    // ------------------------------------------------------------
    reg [23:0] framebuf [0:N_LEDS-1];

    initial begin
        $readmemh(HEX_FILE, framebuf);
    end

    // ------------------------------------------------------------
    // Serializador de un led
    // ------------------------------------------------------------
    reg  [23:0] px_data;
    reg         px_valid;
    reg         do_latch;
    wire        drv_ready;
    wire        latch_done;

    ws2812_led #(
        .CYCLES_BIT  (CYCLES_BIT),
        .CYCLES_T0H  (CYCLES_T0H),
        .CYCLES_T1H  (CYCLES_T1H),
        .CYCLES_RESET(CYCLES_RESET)
    ) u_led (
        .clk       (clk),
        .rst_n     (rst_n),
        .data      (px_data),
        .valid     (px_valid),
        .latch     (do_latch),
        .ready     (drv_ready),
        .latch_done(latch_done),
        .dout      (dout)
    );

    // ------------------------------------------------------------
    // FSM de barrido del arreglo
    // ------------------------------------------------------------
    localparam [1:0] S_READ  = 2'd0,  // leer pixel de memoria
                     S_SEND  = 2'd1,  // entregar pixel al driver
                     S_WAIT  = 2'd2,  // esperar fin del pixel
                     S_LATCH = 2'd3;  // esperar fin del latch

    reg [1:0]    state;
    reg [AW-1:0] addr;

    always @(posedge clk or negedge rst_n) begin
        if (!rst_n) begin
            state      <= S_READ;
            addr       <= {AW{1'b0}};
            px_data    <= 24'd0;
            px_valid   <= 1'b0;
            do_latch   <= 1'b0;
            frame_done <= 1'b0;
        end else begin
            px_valid   <= 1'b0;
            do_latch   <= 1'b0;
            frame_done <= 1'b0;

            case (state)
                // Lectura sincrona de la BRAM
                S_READ: begin
                    px_data <= framebuf[addr];
                    state   <= S_SEND;
                end

                // Pulso de valid cuando el driver este listo
                S_SEND: begin
                    if (drv_ready) begin
                        px_valid <= 1'b1;
                        state    <= S_WAIT;
                    end
                end

                // Esperar a que el driver termine los 24 bits.
                // (un ciclo despues de valid, ready baja; cuando
                //  vuelve a subir el pixel ya salio completo)
                S_WAIT: begin
                    if (!px_valid && drv_ready) begin
                        if (addr == N_LEDS-1) begin
                            addr     <= {AW{1'b0}};
                            do_latch <= 1'b1;
                            state    <= S_LATCH;
                        end else begin
                            addr  <= addr + 1'b1;
                            state <= S_READ;
                        end
                    end
                end

                // Fin del latch -> cuadro completo, refrescar
                S_LATCH: begin
                    if (latch_done) begin
                        frame_done <= 1'b1;
                        state      <= S_READ;
                    end
                end
            endcase
        end
    end

endmodule

tira_led/ws2812_codigo/tb/tb_ws2812_matrix8x8.v
// ============================================================
// tb_ws2812_matrix8x8.v
// Prueba de integracion del arreglo completo:
//   1. Carga la MISMA imagen .hex que el DUT en una memoria
//      de referencia.
//   2. Decodifica la trama serial de 'dout' (64 pixeles x 24 bits)
//      midiendo el ancho de cada pulso.
//   3. Compara pixel por pixel contra la referencia.
//   4. Verifica que despues del pixel 63 llegue el latch (>50 us
//      en bajo) y el pulso frame_done, y que el cuadro se repita.
// ============================================================
`timescale 1ns / 1ps

module tb_ws2812_matrix8x8;

    localparam CLK_PERIOD = 40;   // 25 MHz
    localparam N_LEDS     = 64;

    reg  clk = 0;
    reg  rst_n = 0;
    wire dout;
    wire frame_done;

    integer errors = 0;

    // DUT: usa la ruta del hex relativa a la carpeta de simulacion
    ws2812_matrix8x8 #(
        .HEX_FILE("../img/image.hex")
    ) dut (
        .clk(clk), .rst_n(rst_n),
        .dout(dout), .frame_done(frame_done)
    );

    always #(CLK_PERIOD/2) clk = ~clk;

    // ------------------------------------------------------------
    // Memoria de referencia (misma imagen)
    // ------------------------------------------------------------
    reg [23:0] ref_img [0:N_LEDS-1];
    initial $readmemh("../img/image.hex", ref_img);

    // ------------------------------------------------------------
    // Decodificador de un pixel (24 pulsos)
    // ------------------------------------------------------------
    task decode_pixel(output [23:0] rx);
        integer  i, width;
        realtime t_rise, t_fall;
        begin
            rx = 24'd0;
            for (i = 0; i < 24; i = i + 1) begin
                @(posedge dout);  t_rise = $realtime;
                @(negedge dout);  t_fall = $realtime;
                width = t_fall - t_rise;
                rx = {rx[22:0], (width > 600) ? 1'b1 : 1'b0};
            end
        end
    endtask

    // ------------------------------------------------------------
    // Verificar un cuadro completo
    // ------------------------------------------------------------
    task check_frame(input integer frame_id);
        integer    n, fails;
        reg [23:0] rx;
        begin
            fails = 0;
            for (n = 0; n < N_LEDS; n = n + 1) begin
                decode_pixel(rx);
                if (rx !== ref_img[n]) begin
                    $display("  Pixel %0d: esperado %06h, recibido %06h [ERROR]",
                             n, ref_img[n], rx);
                    fails = fails + 1;
                end
            end
            if (fails == 0)
                $display("Cuadro %0d: 64/64 pixeles correctos [OK]", frame_id);
            errors = errors + fails;
        end
    endtask

    // ------------------------------------------------------------
    // Estimulo principal
    // ------------------------------------------------------------
    realtime t_last_edge, t_gap;
    initial begin
        $dumpfile("tb_ws2812_matrix8x8.vcd");
        $dumpvars(0, tb_ws2812_matrix8x8);

        repeat (4) @(posedge clk);
        rst_n = 1;

        // --- Cuadro 1
        check_frame(1);
        t_last_edge = $realtime;

        // --- Debe llegar frame_done tras el latch
        @(posedge frame_done);
        t_gap = $realtime - t_last_edge;
        $display("Latch entre cuadros: %0d ns (minimo 50000)", t_gap);
        if (t_gap < 50000) begin
            $display("  ERROR: latch demasiado corto");
            errors = errors + 1;
        end

        // --- Cuadro 2 (refresco automatico)
        check_frame(2);

        if (errors == 0) $display("\n== TB_MATRIX: TODAS LAS PRUEBAS PASARON ==");
        else             $display("\n== TB_MATRIX: %0d ERRORES ==", errors);
        $finish;
    end

    // Timeout de seguridad (2 cuadros ~ 2*(64*30us + 100us) < 6 ms)
    initial begin
        #10_000_000;
        $display("ERROR: timeout de simulacion");
        $finish;
    end

endmodule

I2C/ws2812_codigo/sim/tb_ws2812_matrix8x8.vcd
$date
	Thu Jul 16 10:38:24 2026
$end
$version
	Icarus Verilog
$end
$timescale
	1ps
$end
$scope module tb_ws2812_matrix8x8 $end
$var wire 1 ! frame_done $end
$var wire 1 " dout $end
$var parameter 32 # CLK_PERIOD $end
$var parameter 32 $ N_LEDS $end
$var reg 1 % clk $end
$var reg 1 & rst_n $end
$var integer 32 ' errors [31:0] $end
$var real 1 ( t_gap $end
$var real 1 ) t_last_edge $end
$scope module dut $end
$var wire 1 % clk $end
$var wire 1 & rst_n $end
$var wire 1 * latch_done $end
$var wire 1 + drv_ready $end
$var wire 1 " dout $end
$var parameter 32 , AW $end
$var parameter 32 - CYCLES_BIT $end
$var parameter 32 . CYCLES_RESET $end
$var parameter 32 / CYCLES_T0H $end
$var parameter 32 0 CYCLES_T1H $end
$var parameter 128 1 HEX_FILE $end
$var parameter 32 2 N_LEDS $end
$var parameter 2 3 S_LATCH $end
$var parameter 2 4 S_READ $end
$var parameter 2 5 S_SEND $end
$var parameter 2 6 S_WAIT $end
$var reg 6 7 addr [5:0] $end
$var reg 1 8 do_latch $end
$var reg 1 ! frame_done $end
$var reg 24 9 px_data [23:0] $end
$var reg 1 : px_valid $end
$var reg 2 ; state [1:0] $end
$scope module u_led $end
$var wire 1 % clk $end
$var wire 24 < data [23:0] $end
$var wire 1 8 latch $end
$var wire 1 & rst_n $end
$var wire 1 : valid $end
$var wire 1 = rst_done $end
$var wire 1 + ready $end
$var wire 1 " dout $end
$var wire 1 > cur_bit $end
$var wire 1 ? bit_done $end
$var parameter 32 @ CYCLES_BIT $end
$var parameter 32 A CYCLES_RESET $end
$var parameter 32 B CYCLES_T0H $end
$var parameter 32 C CYCLES_T1H $end
$var parameter 2 D S_IDLE $end
$var parameter 2 E S_LATCH $end
$var parameter 2 F S_SHIFT $end
$var reg 5 G bit_cnt [4:0] $end
$var reg 1 * latch_done $end
$var reg 24 H shreg [23:0] $end
$var reg 2 I state [1:0] $end
$scope module u_timer $end
$var wire 1 ? bit_done $end
$var wire 1 > bit_in $end
$var wire 1 % clk $end
$var wire 1 = rst_done $end
$var wire 1 & rst_n $end
$var wire 1 J rst_req $end
$var wire 1 K run $end
$var wire 12 L t_high [11:0] $end
$var wire 1 " dout_level $end
$var parameter 32 M CLK_HZ $end
$var parameter 32 N CW $end
$var parameter 32 O CYCLES_BIT $end
$var parameter 32 P CYCLES_RESET $end
$var parameter 32 Q CYCLES_T0H $end
$var parameter 32 R CYCLES_T1H $end
$var reg 12 S cnt [11:0] $end
$upscope $end
$upscope $end
$upscope $end
$scope task check_frame $end
$var reg 24 T rx [23:0] $end
$var integer 32 U fails [31:0] $end
$var integer 32 V frame_id [31:0] $end
$var integer 32 W n [31:0] $end
$upscope $end
$scope task decode_pixel $end
$var reg 24 X rx [23:0] $end
$var integer 32 Y i [31:0] $end
$var real 1 Z t_fall $end
$var real 1 [ t_rise $end
$var integer 32 \ width [31:0] $end
$upscope $end
$upscope $end
$enddefinitions $end
$comment Show the parameter values. $end
$dumpall
b10100 R
b1010 Q
b100111000100 P
b11111 O
b1100 N
b1011111010111100001000000 M
b1 F
b10 E
b0 D
b10100 C
b1010 B
b100111000100 A
b11111 @
b10 6
b1 5
b0 4
b11 3
b1000000 2
b101110001011100010111101101001011011010110011100101111011010010110110101100001011001110110010100101110011010000110010101111000 1
b10100 0
b1010 /
b100111000100 .
b11111 -
b110 ,
b1000000 $
b101000 #
$end
#0
$dumpvars
bx \
r0 [
r0 Z
bx Y
bx X
bx W
bx V
bx U
bx T
bx S
b0xxxx0 L
xK
xJ
bx I
bx H
bx G
x?
x>
x=
bx <
bx ;
x:
bx 9
x8
bx 7
x+
x*
r0 )
r0 (
b0 '
0&
0%
x"
x!
$end
#20000
b1010 L
0>
0?
0"
0=
b0 S
0*
b0 G
b0 H
1+
0K
0J
b0 I
0!
08
0:
b0 9
b0 <
b0 7
b0 ;
1%
#40000
0%
#60000
1%
#80000
0%
#100000
1%
#120000
0%
#140000
b1 ;
b0 Y
b0 X
b0 W
b0 U
b1 V
1&
1%
#160000
0%
#180000
b10 ;
1:
1%
#200000
0%
#220000
r220 [
1"
0:
0+
1K
b1 I
1%
#240000
0%
#260000
b1 S
1%
#280000
0%
#300000
b10 S
1%
#320000
0%
#340000
b11 S
1%
#360000
0%
#380000
b100 S
1%
#400000
0%
#420000
b101 S
1%
#440000
0%
#460000
b110 S
1%
#480000
0%
#500000
b111 S
1%
#520000
0%
#540000
b1000 S
1%
#560000
0%
#580000
b1001 S
1%
#600000
0%
#620000
b1 Y
b110010000 \
r620 Z
0"
b1010 S
1%
#640000
0%
#660000
b1011 S
1%
#680000
0%
#700000
b1100 S
1%
#720000
0%
#740000
b1101 S
1%
#760000
0%
#780000
b1110 S
1%
#800000
0%
#820000
b1111 S
1%
#840000
0%
#860000
b10000 S
1%
#880000
0%
#900000
b10001 S
1%
#920000
0%
#940000
b10010 S
1%
#960000
0%
#980000
b10011 S
1%
#1000000
0%
#1020000
b10100 S
1%
#1040000
0%
#1060000
b10101 S
1%
#1080000
0%
#1100000
b10110 S
1%
#1120000
0%
#1140000
b10111 S
1%
#1160000
0%
#1180000
b11000 S
1%
#1200000
0%
#1220000
b11001 S
1%
#1240000
0%
#1260000
b11010 S
1%
#1280000
0%
#1300000
b11011 S
1%
#1320000
0%
#1340000
b11100 S
1%
#1360000
0%
#1380000
b11101 S
1%
#1400000
0%
#1420000
1?
b11110 S
1%
#1440000
0%
#1460000
r1460 [
0?
1"
b0 S
b1 G
1%
#1480000
0%
#1500000
b1 S
1%
#1520000
0%
#1540000
b10 S
1%
#1560000
0%
#1580000
b11 S
1%
#1600000
0%
#1620000
b100 S
1%
#1640000
0%
#1660000
b101 S
1%
#1680000
0%
#1700000
b110 S
1%
#1720000
0%
#1740000
b111 S
1%
#1760000
0%
#1780000
b1000 S
1%
#1800000
0%
#1820000
b1001 S
1%
#1840000
0%
#1860000
b10 Y
r1860 Z
0"
b1010 S
1%
#1880000
0%
#1900000
b1011 S
1%
#1920000
0%
#1940000
b1100 S
1%
#1960000
0%
#1980000
b1101 S
1%
#2000000
0%
#2020000
b1110 S
1%
#2040000
0%
#2060000
b1111 S
1%
#2080000
0%
#2100000
b10000 S
1%
#2120000
0%
#2140000
b10001 S
1%
#2160000
0%
#2180000
b10010 S
1%
#2200000
0%
#2220000
b10011 S
1%
#2240000
0%
#2260000
b10100 S
1%
#2280000
0%
#2300000
b10101 S
1%
#2320000
0%
#2340000
b10110 S
1%
#2360000
0%
#2380000
b10111 S
1%
#2400000
0%
#2420000
b11000 S
1%
#2440000
0%
#2460000
b11001 S
1%
#2480000
0%
#2500000
b11010 S
1%
#2520000
0%
#2540000
b11011 S
1%
#2560000
0%
#2580000
b11100 S
1%
#2600000
0%
#2620000
b11101 S
1%
#2640000
0%
#2660000
1?
b11110 S
1%
#2680000
0%
#2700000
r2700 [
0?
1"
b10 G
b0 S
1%
#2720000
0%
#2740000
b1 S
1%
#2760000
0%
#2780000
b10 S
1%
#2800000
0%
#2820000
b11 S
1%
#2840000
0%
#2860000
b100 S
1%
#2880000
0%
#2900000
b101 S
1%
#2920000
0%
#2940000
b110 S
1%
#2960000
0%
#2980000
b111 S
1%
#3000000
0%
#3020000
b1000 S
1%
#3040000
0%
#3060000
b1001 S
1%
#3080000
0%
#3100000
b11 Y
r3100 Z
0"
b1010 S
1%
#3120000
0%
#3140000
b1011 S
1%
#3160000
0%
#3180000
b1100 S
1%
#3200000
0%
#3220000
b1101 S
1%
#3240000
0%
#3260000
b1110 S
1%
#3280000
0%
#3300000
b1111 S
1%
#3320000
0%
#3340000
b10000 S
1%
#3360000
0%
#3380000
b10001 S
1%
#3400000
0%
#3420000
b10010 S
1%
#3440000
0%
#3460000
b10011 S
1%
#3480000
0%
#3500000
b10100 S
1%
#3520000
0%
#3540000
b10101 S
1%
#3560000
0%
#3580000
b10110 S
1%
#3600000
0%
#3620000
b10111 S
1%
#3640000
0%
#3660000
b11000 S
1%
#3680000
0%
#3700000
b11001 S
1%
#3720000
0%
#3740000
b11010 S
1%
#3760000
0%
#3780000
b11011 S
1%
#3800000
0%
#3820000
b11100 S
1%
#3840000
0%
#3860000
b11101 S
1%
#3880000
0%
#3900000
1?
b11110 S
1%
#3920000
0%
#3940000
r3940 [
0?
1"
b0 S
b11 G
1%
#3960000
0%
#3980000
b1 S
1%
#4000000
0%
#4020000
b10 S
1%
#4040000
0%
#4060000
b11 S
1%
#4080000
0%
#4100000
b100 S
1%
#4120000
0%
#4140000
b101 S
1%
#4160000
0%
#4180000
b110 S
1%
#4200000
0%
#4220000
b111 S
1%
#4240000
0%
#4260000
b1000 S
1%
#4280000
0%
#4300000
b1001 S
1%
#4320000
0%
#4340000
b100 Y
r4340 Z
0"
b1010 S
1%
#4360000
0%
#4380000
b1011 S
1%
#4400000
0%
#4420000
b1100 S
1%
#4440000
0%
#4460000
b1101 S
1%
#4480000
0%
#4500000
b1110 S
1%
#4520000
0%
#4540000
b1111 S
1%
#4560000
0%
#4580000
b10000 S
1%
#4600000
0%
#4620000
b10001 S
1%
#4640000
0%
#4660000
b10010 S
1%
#4680000
0%
#4700000
b10011 S
1%
#4720000
0%
#4740000
b10100 S
1%
#4760000
0%
#4780000
b10101 S
1%
#4800000
0%
#4820000
b10110 S
1%
#4840000
0%
#4860000
b10111 S
1%
#4880000
0%
#4900000
b11000 S
1%
#4920000
0%
#4940000
b11001 S
1%
#4960000
0%
#4980000
b11010 S
1%
#5000000
0%
#5020000
b11011 S
1%
#5040000
0%
#5060000
b11100 S
1%
#5080000
0%
#5100000
b11101 S
1%
#5120000
0%
#5140000
1?
b11110 S
1%
#5160000
0%
#5180000
r5180 [
0?
1"
b100 G
b0 S
1%
#5200000
0%
#5220000
b1 S
1%
#5240000
0%
#5260000
b10 S
1%
#5280000
0%
#5300000
b11 S
1%
#5320000
0%
#5340000
b100 S
1%
#5360000
0%
#5380000
b101 S
1%
#5400000
0%
#5420000
b110 S
1%
#5440000
0%
#5460000
b111 S
1%
#5480000
0%
#5500000
b1000 S
1%
#5520000
0%
#5540000
b1001 S
1%
#5560000
0%
#5580000
b101 Y
r5580 Z
0"
b1010 S
1%
#5600000
0%
#5620000
b1011 S
1%
#5640000
0%
#5660000
b1100 S
1%
#5680000
0%
#5700000
b1101 S
1%
#5720000
0%
#5740000
b1110 S
1%
#5760000
0%
#5780000
b1111 S
1%
#5800000
0%
#5820000
b10000 S
1%
#5840000
0%
#5860000
b10001 S
1%
#5880000
0%
#5900000
b10010 S
1%
#5920000
0%
#5940000
b10011 S
1%
#5960000
0%
#5980000
b10100 S
1%
#6000000
0%
#6020000
b10101 S
1%
#6040000
0%
#6060000
b10110 S
1%
#6080000
0%
#6100000
b10111 S
1%
#6120000
0%
#6140000
b11000 S
1%
#6160000
0%
#6180000
b11001 S
1%
#6200000
0%
#6220000
b11010 S
1%
#6240000
0%
#6260000
b11011 S
1%
#6280000
0%
#6300000
b11100 S
1%
#6320000
0%
#6340000
b11101 S
1%
#6360000
0%
#6380000
1?
b11110 S
1%
#6400000
0%
#6420000
r6420 [
0?
1"
b0 S
b101 G
1%
#6440000
0%
#6460000
b1 S
1%
#6480000
0%
#6500000
b10 S
1%
#6520000
0%
#6540000
b11 S
1%
#6560000
0%
#6580000
b100 S
1%
#6600000
0%
#6620000
b101 S
1%
#6640000
0%
#6660000
b110 S
1%
#6680000
0%
#6700000
b111 S
1%
#6720000
0%
#6740000
b1000 S
1%
#6760000
0%
#6780000
b1001 S
1%
#6800000
0%
#6820000
b110 Y
r6820 Z
0"
b1010 S
1%
#6840000
0%
#6860000
b1011 S
1%
#6880000
0%
#6900000
b1100 S
1%
#6920000
0%
#6940000
b1101 S
1%
#6960000
0%
#6980000
b1110 S
1%
#7000000
0%
#7020000
b1111 S
1%
#7040000
0%
#7060000
b10000 S
1%
#7080000
0%
#7100000
b10001 S
1%
#7120000
0%
#7140000
b10010 S
1%
#7160000
0%
#7180000
b10011 S
1%
#7200000
0%
#7220000
b10100 S
1%
#7240000
0%
#7260000
b10101 S
1%
#7280000
0%
#7300000
b10110 S
1%
#7320000
0%
#7340000
b10111 S
1%
#7360000
0%
#7380000
b11000 S
1%
#7400000
0%
#7420000
b11001 S
1%
#7440000
0%
#7460000
b11010 S
1%
#7480000
0%
#7500000
b11011 S
1%
#7520000
0%
#7540000
b11100 S
1%
#7560000
0%
#7580000
b11101 S
1%
#7600000
0%
#7620000
1?
b11110 S
1%
#7640000
0%
#7660000
r7660 [
0?
1"
b110 G
b0 S
1%
#7680000
0%
#7700000
b1 S
1%
#7720000
0%
#7740000
b10 S
1%
#7760000
0%
#7780000
b11 S
1%
#7800000
0%
#7820000
b100 S
1%
#7840000
0%
#7860000
b101 S
1%
#7880000
0%
#7900000
b110 S
1%
#7920000
0%
#7940000
b111 S
1%
#7960000
0%
#7980000
b1000 S
1%
#8000000
0%
#8020000
b1001 S
1%
#8040000
0%
#8060000
b111 Y
r8060 Z
0"
b1010 S
1%
#8080000
0%
#8100000
b1011 S
1%
#8120000
0%
#8140000
b1100 S
1%
#8160000
0%
#8180000
b1101 S
1%
#8200000
0%
#8220000
b1110 S
1%
#8240000
0%
#8260000
b1111 S
1%
#8280000
0%
#8300000
b10000 S
1%
#8320000
0%
#8340000
b10001 S
1%
#8360000
0%
#8380000
b10010 S
1%
#8400000
0%
#8420000
b10011 S
1%
#8440000
0%
#8460000
b10100 S
1%
#8480000
0%
#8500000
b10101 S
1%
#8520000
0%
#8540000
b10110 S
1%
#8560000
0%
#8580000
b10111 S
1%
#8600000
0%
#8620000
b11000 S
1%
#8640000
0%
#8660000
b11001 S
1%
#8680000
0%
#8700000
b11010 S
1%
#8720000
0%
#8740000
b11011 S
1%
#8760000
0%
#8780000
b11100 S
1%
#8800000
0%
#8820000
b11101 S
1%
#8840000
0%
#8860000
1?
b11110 S
1%
#8880000
0%
#8900000
r8900 [
0?
1"
b0 S
b111 G
1%
#8920000
0%
#8940000
b1 S
1%
#8960000
0%
#8980000
b10 S
1%
#9000000
0%
#9020000
b11 S
1%
#9040000
0%
#9060000
b100 S
1%
#9080000
0%
#9100000
b101 S
1%
#9120000
0%
#9140000
b110 S
1%
#9160000
0%
#9180000
b111 S
1%
#9200000
0%
#9220000
b1000 S
1%
#9240000
0%
#9260000
b1001 S
1%
#9280000
0%
#9300000
b1000 Y
r9300 Z
0"
b1010 S
1%
#9320000
0%
#9340000
b1011 S
1%
#9360000
0%
#9380000
b1100 S
1%
#9400000
0%
#9420000
b1101 S
1%
#9440000
0%
#9460000
b1110 S
1%
#9480000
0%
#9500000
b1111 S
1%
#9520000
0%
#9540000
b10000 S
1%
#9560000
0%
#9580000
b10001 S
1%
#9600000
0%
#9620000
b10010 S
1%
#9640000
0%
#9660000
b10011 S
1%
#9680000
0%
#9700000
b10100 S
1%
#9720000
0%
#9740000
b10101 S
1%
#9760000
0%
#9780000
b10110 S
1%
#9800000
0%
#9820000
b10111 S
1%
#9840000
0%
#9860000
b11000 S
1%
#9880000
0%
#9900000
b11001 S
1%
#9920000
0%
#9940000
b11010 S
1%
#9960000
0%
#9980000
b11011 S
1%
#10000000
0%
#10020000
b11100 S
1%
#10040000
0%
#10060000
b11101 S
1%
#10080000
0%
#10100000
1?
b11110 S
1%
#10120000
0%
#10140000
r10140 [
0?
1"
b1000 G
b0 S
1%
#10160000
0%
#10180000
b1 S
1%
#10200000
0%
#10220000
b10 S
1%
#10240000
0%
#10260000
b11 S
1%
#10280000
0%
#10300000
b100 S
1%
#10320000
0%
#10340000
b101 S
1%
#10360000
0%
#10380000
b110 S
1%
#10400000
0%
#10420000
b111 S
1%
#10440000
0%
#10460000
b1000 S
1%
#10480000
0%
#10500000
b1001 S
1%
#10520000
0%
#10540000
b1001 Y
r10540 Z
0"
b1010 S
1%
#10560000
0%
#10580000
b1011 S
1%
#10600000
0%
#10620000
b1100 S
1%
#10640000
0%
#10660000
b1101 S
1%
#10680000
0%
#10700000
b1110 S
1%
#10720000
0%
#10740000
b1111 S
1%
#10760000
0%
#10780000
b10000 S
1%
#10800000
0%
#10820000
b10001 S
1%
#10840000
0%
#10860000
b10010 S
1%
#10880000
0%
#10900000
b10011 S
1%
#10920000
0%
#10940000
b10100 S
1%
#10960000
0%
#10980000
b10101 S
1%
#11000000
0%
#11020000
b10110 S
1%
#11040000
0%
#11060000
b10111 S
1%
#11080000
0%
#11100000
b11000 S
1%
#11120000
0%
#11140000
b11001 S
1%
#11160000
0%
