tira_led/ws2812_codigo/rtl/ws2812_timer.v
// ============================================================
// ws2812_timer.v
// Base de tiempos para el protocolo WS2812 (NRZ de un solo hilo)
// Pensado para la Colorlight i9 (reloj de 25 MHz -> 40 ns/ciclo)
//
// Tiempos del WS2812B:
//   Bit '0':  T0H = 0.40 us  |  T0L = 0.85 us
//   Bit '1':  T1H = 0.80 us  |  T1L = 0.45 us
//   Periodo de bit ~= 1.25 us
//   RESET (latch): linea en bajo > 50 us
//
// A 25 MHz:
//   1.25 us = 31.25 ciclos -> usamos 31 (1.24 us, dentro de tolerancia)
//   0.40 us = 10 ciclos
//   0.80 us = 20 ciclos
//   RESET   = 2500 ciclos (100 us, con margen de sobra)
//
// Funcionamiento:
//   - 'run' habilita el conteo del periodo de bit.
//   - 'bit_in' indica que bit se esta transmitiendo (0/1).
//   - 'dout_level' entrega el nivel que debe tener la linea de datos.
//   - 'bit_done' se pulsa 1 ciclo al terminar cada periodo de bit.
//   - 'rst_req' pide generar el tiempo de RESET/latch; 'rst_done'
//     se pulsa 1 ciclo cuando el tiempo de latch termino.
// ============================================================
`timescale 1ns / 1ps

module ws2812_timer #(
    parameter CLK_HZ       = 25_000_000,
    parameter CYCLES_BIT   = 31,    // ~1.25 us
    parameter CYCLES_T0H   = 10,    // ~0.40 us
    parameter CYCLES_T1H   = 20,    // ~0.80 us
    parameter CYCLES_RESET = 2500   // ~100 us
)(
    input  wire clk,
    input  wire rst_n,      // reset asincrono activo en bajo

    input  wire run,        // habilita el conteo de bits
    input  wire bit_in,     // valor del bit a serializar
    input  wire rst_req,    // solicitar periodo de latch (linea en bajo)

    output wire dout_level, // nivel de la linea de datos WS2812
    output wire bit_done,   // pulso: ultimo ciclo de un periodo de bit
    output wire rst_done    // pulso: ultimo ciclo del periodo de latch
);

    // Ancho suficiente para el contador mas grande
    localparam CW = $clog2(CYCLES_RESET + 1);

    reg [CW-1:0] cnt;

    // 'bit_done' y 'rst_done' son COMBINACIONALES: se activan durante
    // el ultimo ciclo del periodo, de modo que la FSM que consume
    // estas senales cambie de estado en el MISMO flanco en que 'cnt'
    // da la vuelta. Asi no aparecen pulsos espurios en la linea al
    // pasar de un pixel al siguiente.
    assign bit_done = run     && (cnt == CYCLES_BIT   - 1);
    assign rst_done = rst_req && (cnt == CYCLES_RESET - 1);

    // ------------------------------------------------------------
    // Contador de periodo de bit / latch
    // ------------------------------------------------------------
    always @(posedge clk or negedge rst_n) begin
        if (!rst_n) begin
            cnt <= {CW{1'b0}};
        end else begin
            if (run) begin
                if (bit_done) cnt <= {CW{1'b0}};
                else          cnt <= cnt + 1'b1;
            end else if (rst_req) begin
                if (rst_done) cnt <= {CW{1'b0}};
                else          cnt <= cnt + 1'b1;
            end else begin
                cnt <= {CW{1'b0}};
            end
        end
    end

    // ------------------------------------------------------------
    // Nivel de salida: alto durante T0H o T1H segun el bit,
    // bajo el resto del periodo. En latch siempre bajo.
    // ------------------------------------------------------------
    wire [CW-1:0] t_high = bit_in ? CYCLES_T1H[CW-1:0] : CYCLES_T0H[CW-1:0];

    assign dout_level = run ? (cnt < t_high) : 1'b0;

endmodule

tira_led/ws2812_codigo/tb/tb_ws2812_timer.v
// ============================================================
// tb_ws2812_timer.v
// Verifica que el timer genere:
//   - Bit '0': ~0.40 us en alto dentro de un periodo de ~1.24 us
//   - Bit '1': ~0.80 us en alto dentro de un periodo de ~1.24 us
//   - RESET  : ~100 us con la linea en bajo
// Mide los anchos reales con marcas de tiempo y los compara.
// ============================================================
`timescale 1ns / 1ps

module tb_ws2812_timer;

    localparam CLK_PERIOD = 40; // 25 MHz

    reg  clk = 0;
    reg  rst_n = 0;
    reg  run = 0;
    reg  bit_in = 0;
    reg  rst_req = 0;
    wire dout_level, bit_done, rst_done;

    integer errors = 0;

    ws2812_timer dut (
        .clk(clk), .rst_n(rst_n),
        .run(run), .bit_in(bit_in), .rst_req(rst_req),
        .dout_level(dout_level), .bit_done(bit_done), .rst_done(rst_done)
    );

    always #(CLK_PERIOD/2) clk = ~clk;

    // ------------------------------------------------------------
    // Tarea: transmitir un bit y medir T_high y el periodo total
    // ------------------------------------------------------------
    task check_bit(input value, input integer exp_high_ns, input integer exp_period_ns);
        realtime t_start, t_fall, t_end;
        integer  high_ns, period_ns;
        begin
            bit_in = value;
            @(posedge clk);
            run = 1;
            @(posedge dout_level);
            t_start = $realtime;
            @(negedge dout_level);
            t_fall  = $realtime;
            @(posedge bit_done);
            t_end   = $realtime;
            @(posedge clk);
            run = 0;
            @(posedge clk);

            high_ns   = t_fall - t_start;
            period_ns = t_end  - t_start + CLK_PERIOD; // bit_done llega 1 flanco despues

            $display("Bit %0d: T_high = %0d ns (esperado %0d), periodo ~ %0d ns (esperado %0d)",
                     value, high_ns, exp_high_ns, period_ns, exp_period_ns);

            // Tolerancia de +/- 1 ciclo (40 ns)
            if (high_ns < exp_high_ns - CLK_PERIOD || high_ns > exp_high_ns + CLK_PERIOD) begin
                $display("  ERROR: T_high fuera de rango");
                errors = errors + 1;
            end
            if (period_ns < exp_period_ns - 2*CLK_PERIOD || period_ns > exp_period_ns + 2*CLK_PERIOD) begin
                $display("  ERROR: periodo fuera de rango");
                errors = errors + 1;
            end
        end
    endtask

    // ------------------------------------------------------------
    // Estimulo principal
    // ------------------------------------------------------------
    realtime t_rst0, t_rst1;
    integer  rst_ns;

    initial begin
        $dumpfile("tb_ws2812_timer.vcd");
        $dumpvars(0, tb_ws2812_timer);

        // Reset
        repeat (4) @(posedge clk);
        rst_n = 1;
        repeat (2) @(posedge clk);

        // --- Prueba 1: bit '0' (400 ns en alto, 1240 ns de periodo)
        check_bit(1'b0, 400, 1240);

        // --- Prueba 2: bit '1' (800 ns en alto)
        check_bit(1'b1, 800, 1240);

        // --- Prueba 3: la linea debe estar en bajo si run=0
        if (dout_level !== 1'b0) begin
            $display("ERROR: dout_level deberia ser 0 en reposo");
            errors = errors + 1;
        end

        // --- Prueba 4: periodo de RESET (latch) ~100 us
        @(posedge clk);
        t_rst0 = $realtime;
        rst_req = 1;
        @(posedge rst_done);
        t_rst1 = $realtime;
        rst_req = 0;
        rst_ns = t_rst1 - t_rst0;
        $display("RESET: duracion = %0d ns (esperado ~100000, minimo WS2812 = 50000)", rst_ns);
        if (rst_ns < 50000) begin
            $display("  ERROR: el latch es menor a 50 us");
            errors = errors + 1;
        end

        // --- Resultado
        if (errors == 0) $display("\n== TB_TIMER: TODAS LAS PRUEBAS PASARON ==");
        else             $display("\n== TB_TIMER: %0d ERRORES ==", errors);
        $finish;
    end

endmodule

I2C/ws2812_codigo/sim/tb_ws2812_timer.vcd
$date
	Thu Jul 16 10:38:24 2026
$end
$version
	Icarus Verilog
$end
$timescale
	1ps
$end
$scope module tb_ws2812_timer $end
$var wire 1 ! rst_done $end
$var wire 1 " dout_level $end
$var wire 1 # bit_done $end
$var parameter 32 $ CLK_PERIOD $end
$var reg 1 % bit_in $end
$var reg 1 & clk $end
$var reg 1 ' rst_n $end
$var reg 1 ( rst_req $end
$var reg 1 ) run $end
$var integer 32 * errors [31:0] $end
$var integer 32 + rst_ns [31:0] $end
$var real 1 , t_rst0 $end
$var real 1 - t_rst1 $end
$scope module dut $end
$var wire 1 # bit_done $end
$var wire 1 % bit_in $end
$var wire 1 & clk $end
$var wire 1 ! rst_done $end
$var wire 1 ' rst_n $end
$var wire 1 ( rst_req $end
$var wire 1 ) run $end
$var wire 12 . t_high [11:0] $end
$var wire 1 " dout_level $end
$var parameter 32 / CLK_HZ $end
$var parameter 32 0 CW $end
$var parameter 32 1 CYCLES_BIT $end
$var parameter 32 2 CYCLES_RESET $end
$var parameter 32 3 CYCLES_T0H $end
$var parameter 32 4 CYCLES_T1H $end
$var reg 12 5 cnt [11:0] $end
$upscope $end
$scope task check_bit $end
$var reg 1 6 value $end
$var integer 32 7 exp_high_ns [31:0] $end
$var integer 32 8 exp_period_ns [31:0] $end
$var integer 32 9 high_ns [31:0] $end
$var integer 32 : period_ns [31:0] $end
$var real 1 ; t_end $end
$var real 1 < t_fall $end
$var real 1 = t_start $end
$upscope $end
$upscope $end
$enddefinitions $end
$comment Show the parameter values. $end
$dumpall
b10100 4
b1010 3
b100111000100 2
b11111 1
b1100 0
b1011111010111100001000000 /
b101000 $
$end
#0
$dumpvars
r0 =
r0 <
r0 ;
bx :
bx 9
bx 8
bx 7
x6
bx 5
b1010 .
r0 -
r0 ,
bx +
b0 *
0)
0(
0'
0&
0%
0#
0"
0!
$end
#20000
b0 5
1&
#40000
0&
#60000
1&
#80000
0&
#100000
1&
#120000
0&
#140000
1'
1&
#160000
0&
#180000
1&
#200000
0&
#220000
b10011011000 8
b110010000 7
06
1&
#240000
0&
#260000
b1 5
r260 =
1"
1)
1&
#280000
0&
#300000
b10 5
1&
#320000
0&
#340000
b11 5
1&
#360000
0&
#380000
b100 5
1&
#400000
0&
#420000
b101 5
1&
#440000
0&
#460000
b110 5
1&
#480000
0&
#500000
b111 5
1&
#520000
0&
#540000
b1000 5
1&
#560000
0&
#580000
b1001 5
1&
#600000
0&
#620000
r620 <
0"
b1010 5
1&
#640000
0&
#660000
b1011 5
1&
#680000
0&
#700000
b1100 5
1&
#720000
0&
#740000
b1101 5
1&
#760000
0&
#780000
b1110 5
1&
#800000
0&
#820000
b1111 5
1&
#840000
0&
#860000
b10000 5
1&
#880000
0&
#900000
b10001 5
1&
#920000
0&
#940000
b10010 5
1&
#960000
0&
#980000
b10011 5
1&
#1000000
0&
#1020000
b10100 5
1&
#1040000
0&
#1060000
b10101 5
1&
#1080000
0&
#1100000
b10110 5
1&
#1120000
0&
#1140000
b10111 5
1&
#1160000
0&
#1180000
b11000 5
1&
#1200000
0&
#1220000
b11001 5
1&
#1240000
0&
#1260000
b11010 5
1&
#1280000
0&
#1300000
b11011 5
1&
#1320000
0&
#1340000
b11100 5
1&
#1360000
0&
#1380000
b11101 5
1&
#1400000
0&
#1420000
r1420 ;
1#
b11110 5
1&
#1440000
0&
#1460000
b0 5
0#
0)
1&
#1480000
0&
#1500000
b10100 .
1%
b1100100000 7
16
b10010110000 :
b101101000 9
1&
#1520000
0&
#1540000
b1 5
r1540 =
1"
1)
1&
#1560000
0&
#1580000
b10 5
1&
#1600000
0&
#1620000
b11 5
1&
#1640000
0&
#1660000
b100 5
1&
#1680000
0&
#1700000
b101 5
1&
#1720000
0&
#1740000
b110 5
1&
#1760000
0&
#1780000
b111 5
1&
#1800000
0&
#1820000
b1000 5
1&
#1840000
0&
#1860000
b1001 5
1&
#1880000
0&
#1900000
b1010 5
1&
#1920000
0&
#1940000
b1011 5
1&
#1960000
0&
#1980000
b1100 5
1&
#2000000
0&
#2020000
b1101 5
1&
#2040000
0&
#2060000
b1110 5
1&
#2080000
0&
#2100000
b1111 5
1&
#2120000
0&
#2140000
b10000 5
1&
#2160000
0&
#2180000
b10001 5
1&
#2200000
0&
#2220000
b10010 5
1&
#2240000
0&
#2260000
b10011 5
1&
#2280000
0&
#2300000
r2300 <
0"
b10100 5
1&
#2320000
0&
#2340000
b10101 5
1&
#2360000
0&
#2380000
b10110 5
1&
#2400000
0&
#2420000
b10111 5
1&
#2440000
0&
#2460000
b11000 5
1&
#2480000
0&
#2500000
b11001 5
1&
#2520000
0&
#2540000
b11010 5
1&
#2560000
0&
#2580000
b11011 5
1&
#2600000
0&
#2620000
b11100 5
1&
#2640000
0&
#2660000
b11101 5
1&
#2680000
0&
#2700000
r2700 ;
1#
b11110 5
1&
#2720000
0&
#2740000
b0 5
0#
0)
1&
#2760000
0&
#2780000
b1011111000 9
1&
#2800000
0&
#2820000
b1 5
1(
r2820 ,
1&
#2840000
0&
#2860000
b10 5
1&
#2880000
0&
#2900000
b11 5
1&
#2920000
0&
#2940000
b100 5
1&
#2960000
0&
#2980000
b101 5
1&
#3000000
0&
#3020000
b110 5
1&
#3040000
0&
#3060000
b111 5
1&
#3080000
0&
#3100000
b1000 5
1&
#3120000
0&
#3140000
b1001 5
1&
#3160000
0&
#3180000
b1010 5
1&
#3200000
0&
#3220000
b1011 5
1&
#3240000
0&
#3260000
b1100 5
1&
#3280000
0&
#3300000
b1101 5
1&
#3320000
0&
#3340000
b1110 5
1&
#3360000
0&
#3380000
b1111 5
1&
#3400000
0&
#3420000
b10000 5
1&
#3440000
0&
#3460000
b10001 5
1&
#3480000
0&
#3500000
b10010 5
1&
#3520000
0&
#3540000
b10011 5
1&
#3560000
0&
#3580000
b10100 5
1&
#3600000
0&
#3620000
b10101 5
1&
#3640000
0&
#3660000
b10110 5
1&
#3680000
0&
#3700000
b10111 5
1&
#3720000
0&
#3740000
b11000 5
1&
#3760000
0&
#3780000
b11001 5
1&
#3800000
0&
#3820000
b11010 5
1&
#3840000
0&
#3860000
b11011 5
1&
#3880000
0&
#3900000
b11100 5
1&
#3920000
0&
#3940000
b11101 5
1&
#3960000
0&
#3980000
b11110 5
1&
#4000000
0&
#4020000
b11111 5
1&
#4040000
0&
#4060000
b100000 5
1&
#4080000
0&
#4100000
b100001 5
1&
#4120000
0&
#4140000
b100010 5
1&
#4160000
0&
#4180000
b100011 5
1&
#4200000
0&
#4220000
b100100 5
1&
#4240000
0&
#4260000
b100101 5
1&
#4280000
0&
#4300000
b100110 5
1&
#4320000
0&
#4340000
b100111 5
1&
#4360000
0&
#4380000
b101000 5
1&
#4400000
0&
#4420000
b101001 5
1&
#4440000
0&
#4460000
b101010 5
1&
#4480000
0&
#4500000
b101011 5
1&
#4520000
0&
#4540000
b101100 5
1&
#4560000
0&
#4580000
b101101 5
1&
#4600000
0&
#4620000
b101110 5
1&
#4640000
0&
#4660000
b101111 5
1&
#4680000
0&
#4700000
b110000 5
1&
#4720000
0&
#4740000
b110001 5
1&
#4760000
0&
#4780000
b110010 5
1&
#4800000
0&
#4820000
b110011 5
1&
#4840000
0&
#4860000
b110100 5
1&
#4880000
0&
#4900000
b110101 5
1&
#4920000
0&
#4940000
b110110 5
1&
#4960000
0&
#4980000
b110111 5
1&
#5000000
0&
#5020000
b111000 5
1&
#5040000
0&
#5060000
b111001 5
1&
#5080000
0&
#5100000
b111010 5
1&
#5120000
0&
#5140000
b111011 5
1&
#5160000
0&
#5180000
b111100 5
1&
#5200000
0&
#5220000
b111101 5
1&
#5240000
0&
#5260000
b111110 5
1&
#5280000
0&
#5300000
b111111 5
1&
#5320000
0&
#5340000
b1000000 5
1&
#5360000
0&
#5380000
b1000001 5
1&
#5400000
0&
#5420000
b1000010 5
1&
#5440000
0&
#5460000
b1000011 5
1&
#5480000
0&
#5500000
b1000100 5
1&
#5520000
0&
#5540000
b1000101 5
1&
#5560000
0&
#5580000
b1000110 5
1&
#5600000
0&
#5620000
b1000111 5
1&
#5640000
0&
#5660000
b1001000 5
1&
#5680000
0&
#5700000
b1001001 5
1&
#5720000
0&
#5740000
b1001010 5
1&
#5760000
0&
#5780000
b1001011 5
1&
#5800000
0&
#5820000
b1001100 5
1&
#5840000
0&
#5860000
b1001101 5
1&
#5880000
0&
#5900000
b1001110 5
1&
#5920000
0&
#5940000
b1001111 5
1&
#5960000
0&
#5980000
b1010000 5
1&
#6000000
0&
#6020000
b1010001 5
1&
#6040000
0&
#6060000
b1010010 5
1&
#6080000
0&
#6100000
b1010011 5
1&
#6120000
0&
#6140000
b1010100 5
1&
#6160000
0&
#6180000
b1010101 5
1&
#6200000
0&
#6220000
b1010110 5
1&
#6240000
0&
#6260000
b1010111 5
1&
#6280000
0&
#6300000
b1011000 5
1&
#6320000
0&
#6340000
b1011001 5
1&
#6360000
0&
#6380000
b1011010 5
1&
#6400000
0&
#6420000
b1011011 5
1&
#6440000
0&
#6460000
b1011100 5
1&
#6480000
0&
#6500000
b1011101 5
1&
#6520000
0&
#6540000
b1011110 5
1&
#6560000
0&
#6580000
b1011111 5
1&
#6600000
0&
#6620000
b1100000 5
1&
#6640000
0&
#6660000
b1100001 5
1&
#6680000
0&
#6700000
b1100010 5
1&
#6720000
0&
#6740000
b1100011 5
1&
#6760000
0&
#6780000
b1100100 5
1&
#6800000
0&
#6820000
b1100101 5
1&
#6840000
0&
#6860000
b1100110 5
1&
#6880000
0&
#6900000
b1100111 5
1&
#6920000
0&
#6940000
b1101000 5
1&
#6960000
0&
#6980000
b1101001 5
1&
#7000000
0&
#7020000
b1101010 5
1&
#7040000
0&
#7060000
b1101011 5
1&
#7080000
0&
#7100000
b1101100 5
1&
#7120000
0&
#7140000
b1101101 5
1&
#7160000
0&
#7180000
b1101110 5
1&
#7200000
0&
#7220000
b1101111 5
1&
#7240000
0&
#7260000
b1110000 5
1&
#7280000
0&
#7300000
b1110001 5
1&
#7320000
0&
#7340000
b1110010 5
1&
#7360000
0&
#7380000
b1110011 5
1&
#7400000
0&
#7420000
b1110100 5
1&
#7440000
0&
#7460000
b1110101 5
1&
#7480000
0&
#7500000
b1110110 5
1&
#7520000
0&
#7540000
b1110111 5
1&
#7560000
0&
#7580000
b1111000 5
1&
#7600000
0&
#7620000
b1111001 5
1&
#7640000
0&
#7660000
b1111010 5
1&
#7680000
0&
#7700000
b1111011 5
1&
#7720000
0&
#7740000
b1111100 5
1&
#7760000
0&
#7780000
b1111101 5
1&
#7800000
0&
#7820000
b1111110 5
1&
#7840000
0&
#7860000
b1111111 5
1&
#7880000
0&
#7900000
b10000000 5
1&
#7920000
0&
#7940000
b10000001 5
1&
#7960000
0&
#7980000
b10000010 5
1&
#8000000
0&
#8020000
b10000011 5
1&
#8040000
0&
#8060000
b10000100 5
1&
#8080000
0&
#8100000
b10000101 5
1&
#8120000
0&
#8140000
b10000110 5
1&
#8160000
0&
#8180000
b10000111 5
1&
#8200000
0&
#8220000
b10001000 5
1&
#8240000
0&
#8260000
b10001001 5
1&
#8280000
0&
#8300000
b10001010 5
1&
#8320000
0&
#8340000
b10001011 5
1&
#8360000
0&
#8380000
b10001100 5
1&
#8400000
0&
#8420000
b10001101 5
1&
#8440000
0&
#8460000
b10001110 5
1&
#8480000
0&
#8500000
b10001111 5
1&
#8520000
0&
#8540000
b10010000 5
1&
#8560000
0&
#8580000
b10010001 5
1&
#8600000
0&
#8620000
b10010010 5
1&
#8640000
0&
#8660000
b10010011 5
1&
#8680000
0&
#8700000
b10010100 5
1&
#8720000
0&
#8740000
b10010101 5
1&
#8760000
0&
#8780000
b10010110 5
1&
#8800000
0&
#8820000
b10010111 5
1&
#8840000
0&
#8860000
b10011000 5
1&
#8880000
0&
#8900000
b10011001 5
1&
#8920000
0&
#8940000
b10011010 5
1&
#8960000
0&
#8980000
b10011011 5
1&
#9000000
0&
#9020000
b10011100 5
1&
#9040000
0&
#9060000
b10011101 5
1&
#9080000
0&
#9100000
b10011110 5
1&
#9120000
0&
#9140000
b10011111 5
1&
#9160000
0&
#9180000
b10100000 5
1&
#9200000
0&
#9220000
b10100001 5
1&
#9240000
0&
#9260000
b10100010 5
1&
#9280000
0&
#9300000
b10100011 5
1&
#9320000
0&
#9340000
b10100100 5
1&
#9360000
0&
#9380000
b10100101 5
1&
#9400000
0&
#9420000
b10100110 5
1&
#9440000
0&
#9460000
b10100111 5
1&
#9480000
0&
#9500000
b10101000 5
1&
#9520000
0&
#9540000
b10101001 5
1&
#9560000
0&
#9580000
b10101010 5
1&
#9600000
0&
#9620000
b10101011 5
1&
#9640000
0&
#9660000
b10101100 5
1&
#9680000
0&
#9700000
b10101101 5
1&
#9720000
0&
#9740000
b10101110 5
1&
#9760000
0&
#9780000
b10101111 5
1&
#9800000
0&
#9820000
b10110000 5
1&
#9840000
0&
#9860000
b10110001 5
1&
#9880000
0&
#9900000
b10110010 5
1&
#9920000
0&
#9940000
b10110011 5
1&
#9960000
0&
#9980000
b10110100 5
1&
#10000000
0&
#10020000
b10110101 5
1&
#10040000
0&
#10060000
b10110110 5
1&
#10080000
0&
#10100000
b10110111 5
1&
#10120000
0&
#10140000
b10111000 5
1&
#10160000
0&
#10180000
b10111001 5
1&
#10200000
0&
#10220000
b10111010 5
1&
#10240000
0&
#10260000
b10111011 5
1&
#10280000
0&
#10300000
b10111100 5
1&
#10320000
0&
#10340000
b10111101 5
1&
#10360000
0&
#10380000
b10111110 5
1&
#10400000
0&
#10420000
b10111111 5
1&
#10440000
0&
#10460000
b11000000 5
1&
#10480000
0&
#10500000
b11000001 5
1&
#10520000
0&
#10540000
b11000010 5
1&
#10560000
0&
#10580000
b11000011 5
1&
#10600000
0&
#10620000
b11000100 5
1&
#10640000
0&
#10660000
b11000101 5
1&
#10680000
0&
#10700000
b11000110 5
1&
#10720000
0&
#10740000
b11000111 5
1&
#10760000
0&
#10780000
b11001000 5
1&
#10800000
0&
#10820000
b11001001 5
1&
#10840000
0&
#10860000
b11001010 5
1&
#10880000
0&
#10900000
b11001011 5
1&
#10920000
0&
#10940000
b11001100 5
1&
#10960000
0&
#10980000
b11001101 5
1&
#11000000
0&
#11020000
b11001110 5
1&
#11040000
0&
#11060000
b11001111 5
1&
#11080000
0&
#11100000
b11010000 5
1&
#11120000
0&
#11140000
b11010001 5
1&
#11160000
0&
#11180000
b11010010 5
1&
#11200000
0&
#11220000
b11010011 5
1&
#11240000
0&
#11260000
b11010100 5
1&
#11280000
0&
#11300000
b11010101 5
1&
#11320000
0&
#11340000
b11010110 5
1&
#11360000
0&
#11380000
b11010111 5
1&
#11400000
0&
#11420000
b11011000 5
1&
#11440000
0&
#11460000
b11011001 5
1&
#11480000
0&
#11500000
b11011010 5
1&
#11520000
0&
#11540000
b11011011 5
1&
#11560000
0&
#11580000
b11011100 5
1&
#11600000
0&
#11620000
b11011101 5
1&
#11640000
0&
#11660000
b11011110 5
1&
#11680000
0&
#11700000
b11011111 5
1&
#11720000
0&
#11740000
b11100000 5
1&
#11760000
0&
#11780000
b11100001 5
1&
#11800000
0&
#11820000
b11100010 5
1&
#11840000
0&
#11860000
b11100011 5
1&
#11880000
0&
#11900000
b11100100 5
1&
#11920000
0&
#11940000
b11100101 5
1&
#11960000
0&
#11980000
b11100110 5
1&
#12000000
0&
#12020000
b11100111 5
1&
#12040000
0&
#12060000
b11101000 5
1&
#12080000
0&
#12100000
b11101001 5
1&
#12120000
0&
#12140000
b11101010 5
1&
#12160000
0&
#12180000
b11101011 5
1&
#12200000
0&
#12220000
b11101100 5
1&
#12240000
0&
#12260000
b11101101 5
1&
#12280000
0&
#12300000
b11101110 5
1&
#12320000
0&
#12340000
b11101111 5
1&
#12360000
0&
#12380000
b11110000 5
1&
#12400000
0&
#12420000
b11110001 5
1&
#12440000
0&
#12460000
b11110010 5
1&
#12480000
0&
#12500000
b11110011 5
1&
#12520000
0&
#12540000
b11110100 5
1&
#12560000
0&
#12580000
b11110101 5
1&
#12600000
0&
#12620000
b11110110 5
1&
#12640000
0&
#12660000
b11110111 5
1&
#12680000
0&
#12700000
b11111000 5
1&
#12720000
0&
#12740000
b11111001 5
1&
#12760000
0&
#12780000
b11111010 5
1&
#12800000
0&
#12820000
b11111011 5
1&
#12840000
0&
#12860000
b11111100 5
1&
#12880000
0&
#12900000
b11111101 5
1&
#12920000
0&
#12940000
b11111110 5
1&
#12960000
0&
#12980000
b11111111 5
1&
#13000000
0&
#13020000
b100000000 5
1&
#13040000
0&
#13060000
b100000001 5
1&
#13080000
0&
#13100000
b100000010 5
1&
#13120000
0&
#13140000
b100000011 5
1&
#13160000
0&
#13180000
b100000100 5
1&
#13200000
0&
#13220000
b100000101 5
1&
#13240000
0&
#13260000
b100000110 5
1&
#13280000
0&
#13300000
b100000111 5
1&
#13320000
0&
#13340000
b100001000 5
1&
#13360000
0&
#13380000
b100001001 5
1&
#13400000
0&
#13420000
b100001010 5
1&
#13440000
0&
#13460000
b100001011 5
1&
#13480000
0&
#13500000
b100001100 5
1&
#13520000
0&
#13540000
b100001101 5
1&
#13560000
0&
#13580000
b100001110 5
1&
#13600000
0&
#13620000
b100001111 5
1&
#13640000
0&
#13660000
b100010000 5
1&
#13680000
0&
#13700000
b100010001 5
1&
#13720000
0&
#13740000
b100010010 5
1&
#13760000
0&
#13780000
b100010011 5
1&
#13800000
0&
#13820000
b100010100 5
1&
#13840000
0&
#13860000
b100010101 5
1&
#13880000
0&
#13900000
b100010110 5
1&
#13920000
0&
#13940000
b100010111 5
1&
#13960000
0&
#13980000
b100011000 5
1&
#14000000
0&
#14020000
b100011001 5
1&
#14040000
0&
#14060000
b100011010 5
1&
#14080000
0&
#14100000
b100011011 5
1&
#14120000
0&
#14140000
b100011100 5
1&
#14160000
0&
#14180000
b100011101 5
1&
#14200000
0&
#14220000
b100011110 5
1&
#14240000
0&
#14260000
b100011111 5
1&
#14280000
0&
#14300000
b100100000 5
1&
#14320000
0&
#14340000
b100100001 5
1&
#14360000
0&
#14380000
b100100010 5
1&
#14400000
0&
#14420000
b100100011 5
1&
#14440000
0&
#14460000
b100100100 5
1&
#14480000
0&
#14500000
b100100101 5
1&
#14520000
0&
#14540000
b100100110 5
1&
#14560000
0&
#14580000
b100100111 5
1&
#14600000
0&
#14620000
b100101000 5
1&
#14640000
0&
#14660000
b100101001 5
1&
#14680000
0&
#14700000
b100101010 5
1&
#14720000
0&
#14740000
b100101011 5
1&
#14760000
0&
#14780000
b100101100 5
1&
#14800000
0&
#14820000
b100101101 5
1&
#14840000
0&
#14860000
b100101110 5
1&
#14880000
0&
#14900000
b100101111 5
1&
#14920000
0&
#14940000
b100110000 5
1&
#14960000
0&
#14980000
b100110001 5
1&
#15000000
0&
#15020000
b100110010 5
1&
#15040000
0&
#15060000
b100110011 5
1&
#15080000
0&
#15100000
b100110100 5
1&
#15120000
0&
#15140000
b100110101 5
1&
#15160000
0&
#15180000
b100110110 5
1&
#15200000
0&
#15220000
b100110111 5
1&
#15240000
0&
#15260000
b100111000 5
1&
#15280000
0&
#15300000
b100111001 5
1&
#15320000
0&
#15340000
b100111010 5
1&
#15360000
0&
#15380000
b100111011 5
1&
#15400000
0&
#15420000
b100111100 5
1&
#15440000
0&
#15460000
b100111101 5
1&
#15480000
0&
#15500000
b100111110 5
1&
#15520000
0&
#15540000
b100111111 5
1&
#15560000
0&
#15580000
b101000000 5
1&
#15600000
0&
#15620000
b101000001 5
1&
#15640000
0&
#15660000
b101000010 5
1&
#15680000
0&
#15700000
b101000011 5
1&
#15720000
0&
#15740000
b101000100 5
1&
#15760000
0&
#15780000
b101000101 5
1&
#15800000
0&
#15820000
b101000110 5
1&
#15840000
0&
#15860000
b101000111 5
1&
#15880000
0&
#15900000
b101001000 5
1&
#15920000
0&
#15940000
b101001001 5
1&
#15960000
0&
#15980000
b101001010 5
1&
#16000000
0&
#16020000
b101001011 5
1&
#16040000
0&
#16060000
b101001100 5
1&
#16080000
0&
#16100000
b101001101 5
1&
#16120000
0&
#16140000
b101001110 5
1&
#16160000
0&
#16180000
b101001111 5
1&
#16200000
0&
#16220000
b101010000 5
1&
#16240000
0&
#16260000
b101010001 5
1&
#16280000
0&
#16300000
b101010010 5
1&
#16320000
0&
#16340000
b101010011 5
1&
#16360000
0&
#16380000
b101010100 5
1&
#16400000
0&
#16420000
b101010101 5
1&
#16440000
0&
#16460000
b101010110 5
1&
#16480000
0&
#16500000
b101010111 5
1&
#16520000
0&
#16540000
b101011000 5
1&
#16560000
0&
#16580000
b101011001 5
1&
#16600000
0&
#16620000
b101011010 5
1&
#16640000
0&
#16660000
b101011011 5
1&
#16680000
0&
#16700000
b101011100 5
1&
#16720000
0&
#16740000
b101011101 5
1&
#16760000
0&
#16780000
b101011110 5
1&
#16800000
0&
#16820000
b101011111 5
1&
#16840000
0&
#16860000
b101100000 5
1&
#16880000
0&
#16900000
b101100001 5
1&
#16920000
0&
#16940000
b101100010 5
1&
#16960000
0&
#16980000
b101100011 5
1&
#17000000
0&
#17020000
b101100100 5
1&
#17040000
0&
#17060000
b101100101 5
1&
#17080000
0&
#17100000
b101100110 5
1&
#17120000
0&
#17140000
b101100111 5
1&
#17160000
0&
#17180000
b101101000 5
1&
#17200000
0&
#17220000
b101101001 5
1&
#17240000
0&
#17260000
b101101010 5
1&
#17280000
0&
#17300000
b101101011 5
1&
#17320000
0&
#17340000
b101101100 5
1&
#17360000
0&
#17380000
b101101101 5
1&
#17400000
0&
#17420000
b101101110 5
1&
#17440000
0&
#17460000
b101101111 5
1&
#17480000
0&
#17500000
b101110000 5
1&
#17520000
0&
#17540000
b101110001 5
1&
#17560000
0&
#17580000
b101110010 5
1&
#17600000
0&
#17620000
b101110011 5
1&
#17640000
0&
#17660000
b101110100 5
1&
#17680000
0&
#17700000
b101110101 5
1&
#17720000
0&
#17740000
b101110110 5
1&
#17760000
0&
#17780000
b101110111 5
1&
#17800000
0&
#17820000
b101111000 5
1&
#17840000
0&
#17860000
b101111001 5
1&
#17880000
0&
#17900000
b101111010 5
1&
#17920000
0&
#17940000
b101111011 5
1&
#17960000
0&
#17980000
b101111100 5
1&
#18000000
0&
#18020000
b101111101 5
1&
#18040000
0&
#18060000
b101111110 5
1&
#18080000
0&
#18100000
b101111111 5
1&
#18120000
0&
#18140000
b110000000 5
1&
#18160000
0&
#18180000
b110000001 5
1&
#18200000
0&
#18220000
b110000010 5
1&
#18240000
0&
#18260000
b110000011 5
1&
#18280000
0&
#18300000
b110000100 5
1&
#18320000
0&
#18340000
b110000101 5
1&
#18360000
0&
#18380000
b110000110 5
1&
#18400000
0&
#18420000
b110000111 5
1&
#18440000
0&
#18460000
b110001000 5
1&
#18480000
0&
#18500000
b110001001 5
1&
#18520000
0&
#18540000
b110001010 5
1&
#18560000
0&
#18580000
b110001011 5
1&
#18600000
0&
#18620000
b110001100 5
1&
#18640000
0&
#18660000
b110001101 5
1&
#18680000
0&
#18700000
b110001110 5
1&
#18720000
0&
#18740000
b110001111 5
1&
#18760000
0&
#18780000
b110010000 5
1&
#18800000
0&
