Litex_calculadora/addsub_16/control_addsub.v
module control_addsub( clk , rst , init , last , done , load , calc );

 input clk;
 input rst;
 input init;
 input last;

 output reg done;
 output reg load;
 output reg calc;

 parameter START   = 2'b00;
 parameter LOAD    = 2'b01;
 parameter COMPUTE = 2'b10;
 parameter END     = 2'b11;

 reg [1:0] state;

 initial begin
  done  = 0;
  load  = 0;
  calc  = 0;
  state = 0;
 end

always @(posedge clk) begin
    if (rst) begin
      state = START;
    end else begin
    case(state)

      START:begin
        if(init)
          state = LOAD;
        else
          state = START;
      end

     LOAD: begin
        state = COMPUTE;
     end

     COMPUTE: begin
        if(last)
          state = END;
        else
          state = COMPUTE;
     end

     END:begin
        if(init)
          state = START;
        else
          state = END;
     end

     default: state = START;
   endcase
  end
end


always@(*) begin
    case(state)

      START:begin
        done  = 0;
        load  = 0;
        calc  = 0;
      end

     LOAD: begin
        done  = 0;
        load  = 1;
        calc  = 0;
     end

     COMPUTE: begin
        done  = 0;
        load  = 0;
        calc  = 1;
     end

     END:begin
        done  = 1;
        load  = 0;
        calc  = 0;
     end

     default: begin
        done  = 0;
        load  = 1;
        calc  = 0;
     end
   endcase
end

`ifdef BENCH
reg [8*40:1] state_name;
always @(*) begin
  case(state)
    START    : state_name = "START";
    LOAD     : state_name = "LOAD";
    COMPUTE  : state_name = "COMPUTE";
    END      : state_name = "END";
  endcase
end
`endif

endmodule

Litex_calculadora/addsub_16/count_addsub.v
module count_addsub (clk, load, inc, last);
  input clk;
  input load;
  input inc;
  output last;
  reg [4:0]cnt;

  initial cnt = 5'h0;

  always @(negedge clk)
    if(load) cnt = 5'h0;
    else if(inc) cnt = cnt + 5'h1;
    else cnt = cnt;

  // 16 shift/add(or subtract) iterations are needed to serially process a
  // 16-bit operand pair; `last` is sampled by control_addsub *after* the
  // counter's post-iteration increment, so the threshold is 16 (not 15) to
  // avoid stopping one iteration early.
  assign last = (cnt == 5'd16);

endmodule

Litex_calculadora/addsub_16/res_addsub.v
module res_addsub (clk, bit_in, load, shift, result);
  input clk;
  input bit_in;
  input load;
  input shift;
  output reg [15:0]result;

initial result = 16'h0000;

always @(negedge clk)
  if(load)
    result = 16'h0000;
  else if(shift)
    result = {bit_in, result[15:1]};
  else
    result = result;

endmodule

Litex_calculadora/addsub_16/ov_addsub.v
module ov_addsub (clk, ov_in, load, upd, overflow);
  input clk;
  input ov_in;
  input load;
  input upd;
  output reg overflow;

initial overflow = 1'b0;

always @(negedge clk)
  if(load)
    overflow = 1'b0;
  else if(upd)
    overflow = ov_in;
  else
    overflow = overflow;

endmodule

Litex_calculadora/addsub_16/carry_addsub.v
module carry_addsub (clk, cin_init, cout, load, upd, carry);
  input clk;
  input cin_init;
  input cout;
  input load;
  input upd;
  output reg carry;

initial carry = 1'b0;

always @(negedge clk)
  if(load)
    carry = cin_init;
  else if(upd)
    carry = cout;
  else
    carry = carry;

endmodule

Litex_calculadora/addsub_16/fa_addsub.v
module fa_addsub (a, b, cin, sum, cout);
  input  a;
  input  b;
  input  cin;
  output sum;
  output cout;

  assign sum  = a ^ b ^ cin;
  assign cout = (a & b) | (a & cin) | (b & cin);

endmodule

Litex_calculadora/addsub_16/srb_addsub.v
module srb_addsub (clk, in_B, shift, load, s_B);
  input clk;
  input [15:0]in_B;
  input load;
  input shift;
  output reg [15:0]s_B;

always @(negedge clk)
  if(load)
     s_B = in_B ;
  else
   begin
    if(shift) s_B = s_B >> 1;
    else s_B = s_B;
   end

endmodule

Litex_calculadora/addsub_16/sra_addsub.v
module sra_addsub (clk, in_A, shift, load, s_A);
  input clk;
  input [15:0]in_A;
  input load;
  input shift;
  output reg [15:0]s_A;

always @(negedge clk)
  if(load)
     s_A = in_A ;
  else
   begin
    if(shift) s_A = s_A >> 1;
    else s_A = s_A;
   end

endmodule

Litex_calculadora/addsub_16/addsub_16.v
module addsub_16(clk , rst , init , A , B , sub , result , carry , overflow , done);

  input rst;
  input clk;
  input init;
  input [15:0] A;
  input [15:0] B;
  input sub;
  output [15:0] result;
  output carry;
  output overflow;
  output done;

  wire w_load;
  wire w_calc;
  wire w_last;

  wire [15:0] w_Beff;
  wire [15:0] w_sA;
  wire [15:0] w_sB;

  wire w_sum;
  wire w_cout;
  wire w_ov_in;

  // sub=1 selects A-B: invert B and inject the "+1" of two's complement as
  // the initial carry-in (cin_init below), turning the adder into a subtractor.
  assign w_Beff = B ^ {16{sub}};

  sra_addsub sra0 (.clk(clk), .in_A(A)     , .shift(w_calc) , .load(w_load) , .s_A(w_sA));
  srb_addsub srb0 (.clk(clk), .in_B(w_Beff), .shift(w_calc) , .load(w_load) , .s_B(w_sB));

  fa_addsub  fa0  (.a(w_sA[0]), .b(w_sB[0]), .cin(carry), .sum(w_sum), .cout(w_cout));

  carry_addsub carry0 (.clk(clk), .cin_init(sub), .cout(w_cout), .load(w_load), .upd(w_calc), .carry(carry));

  // overflow = carry-in to the MSB stage XOR carry-out of the MSB stage,
  // continuously recomputed and only its value after the final iteration matters.
  assign w_ov_in = carry ^ w_cout;
  ov_addsub ov0 (.clk(clk), .ov_in(w_ov_in), .load(w_load), .upd(w_calc), .overflow(overflow));

  res_addsub res0 (.clk(clk), .bit_in(w_sum), .load(w_load), .shift(w_calc), .result(result));

  count_addsub count0 (.clk(clk), .load(w_load), .inc(w_calc), .last(w_last));

  control_addsub control0 (.clk(clk), .rst(rst), .init(init), .last(w_last), .done(done), .load(w_load), .calc(w_calc));

endmodule

Litex_calculadora/addsub_16/addsub_16_TB.v
`timescale 1ns / 1ps
`define SIMULATION
module addsub_16_TB;
   reg  clk;
   reg  rst;
   reg  init;
   reg  sub;
   reg  [15:0]A;
   reg  [15:0]B;
   wire [15:0] result;
   wire carry;
   wire overflow;
   wire done;

   integer errors;

   addsub_16 uut (.clk(clk) , .rst(rst) , .init(init) , .A(A) , .B(B) , .sub(sub) ,
                  .result(result) , .carry(carry) , .overflow(overflow) , .done(done));

   parameter PERIOD          = 20;
   parameter real DUTY_CYCLE = 0.5;

   initial begin
     clk = 0;
     forever
       begin
         clk = 1'b0;
         #(PERIOD-(PERIOD*DUTY_CYCLE)) clk = 1'b1;
         #(PERIOD*DUTY_CYCLE);
       end
   end

   task run_case;
     input [15:0] t_A;
     input [15:0] t_B;
     input        t_sub;
     input [15:0] t_result;
     input        t_carry;
     input        t_overflow;
     begin
       @(negedge clk);
       A = t_A; B = t_B; sub = t_sub;
       init = 1;
       @(negedge clk);
       @(negedge clk);
       init = 0;
       wait(done == 1'b1);
       @(negedge clk);
       if (result != t_result || carry != t_carry || overflow != t_overflow) begin
         errors = errors + 1;
         $display("FAIL: A=%h B=%h sub=%b -> result=%h carry=%b overflow=%b (expected result=%h carry=%b overflow=%b)",
                    t_A, t_B, t_sub, result, carry, overflow, t_result, t_carry, t_overflow);
       end else begin
         $display("PASS: A=%h B=%h sub=%b -> result=%h carry=%b overflow=%b",
                    t_A, t_B, t_sub, result, carry, overflow);
       end
     end
   endtask

   initial begin
     errors = 0;
     rst = 1; init = 0; sub = 0; A = 0; B = 0;
     @(negedge clk);
     @(negedge clk);
     rst = 0;

     // A + B, no carry/overflow
     run_case(16'h00F7, 16'h007F, 1'b0, 16'h0176, 1'b0, 1'b0);
     // A - B, A > B: no borrow (carry=1)
     run_case(16'h0064, 16'h0032, 1'b1, 16'h0032, 1'b1, 1'b0);
     // A - B, A < B: borrow (carry=0), result wraps in two's complement
     run_case(16'h0032, 16'h0064, 1'b1, 16'hFFCE, 1'b0, 1'b0);
     // unsigned add overflow (carry out), no signed overflow (-1 + 1 = 0)
     run_case(16'hFFFF, 16'h0001, 1'b0, 16'h0000, 1'b1, 1'b0);
     // signed add overflow: 32767 + 1 -> -32768
     run_case(16'h7FFF, 16'h0001, 1'b0, 16'h8000, 1'b0, 1'b1);
     // signed subtract overflow: -32768 - 1 -> 32767
     run_case(16'h8000, 16'h0001, 1'b1, 16'h7FFF, 1'b1, 1'b1);

     if (errors == 0)
       $display("ALL TESTS PASSED");
     else
       $display("%0d TEST(S) FAILED", errors);

     $finish;
   end

   initial begin: TEST_CASE
     $dumpfile("addsub_16_TB.vcd");
     $dumpvars(-1, uut);
   end
endmodule

Litex_calculadora/addsub_16/addsub_16_TB.vcd
$date
	Thu Jul 16 10:20:40 2026
$end
$version
	Icarus Verilog
$end
$timescale
	1ps
$end
$scope module addsub_16_TB $end
$scope module uut $end
$var wire 16 ! A [15:0] $end
$var wire 16 " B [15:0] $end
$var wire 1 # clk $end
$var wire 1 $ init $end
$var wire 1 % rst $end
$var wire 1 & sub $end
$var wire 16 ' w_Beff [15:0] $end
$var wire 1 ( w_ov_in $end
$var wire 1 ) w_sum $end
$var wire 16 * w_sB [15:0] $end
$var wire 16 + w_sA [15:0] $end
$var wire 1 , w_load $end
$var wire 1 - w_last $end
$var wire 1 . w_cout $end
$var wire 1 / w_calc $end
$var wire 16 0 result [15:0] $end
$var wire 1 1 overflow $end
$var wire 1 2 done $end
$var wire 1 3 carry $end
$scope module carry0 $end
$var wire 1 & cin_init $end
$var wire 1 # clk $end
$var wire 1 / upd $end
$var wire 1 , load $end
$var wire 1 . cout $end
$var reg 1 3 carry $end
$upscope $end
$scope module control0 $end
$var wire 1 # clk $end
$var wire 1 $ init $end
$var wire 1 % rst $end
$var wire 1 - last $end
$var parameter 2 4 COMPUTE $end
$var parameter 2 5 END $end
$var parameter 2 6 LOAD $end
$var parameter 2 7 START $end
$var reg 1 / calc $end
$var reg 1 2 done $end
$var reg 1 , load $end
$var reg 2 8 state [1:0] $end
$var reg 320 9 state_name [320:1] $end
$upscope $end
$scope module count0 $end
$var wire 1 # clk $end
$var wire 1 / inc $end
$var wire 1 , load $end
$var wire 1 - last $end
$var reg 5 : cnt [4:0] $end
$upscope $end
$scope module fa0 $end
$var wire 1 ; a $end
$var wire 1 < b $end
$var wire 1 3 cin $end
$var wire 1 . cout $end
$var wire 1 ) sum $end
$upscope $end
$scope module ov0 $end
$var wire 1 # clk $end
$var wire 1 , load $end
$var wire 1 ( ov_in $end
$var wire 1 / upd $end
$var reg 1 1 overflow $end
$upscope $end
$scope module res0 $end
$var wire 1 ) bit_in $end
$var wire 1 # clk $end
$var wire 1 , load $end
$var wire 1 / shift $end
$var reg 16 = result [15:0] $end
$upscope $end
$scope module sra0 $end
$var wire 1 # clk $end
$var wire 16 > in_A [15:0] $end
$var wire 1 , load $end
$var wire 1 / shift $end
$var reg 16 ? s_A [15:0] $end
$upscope $end
$scope module srb0 $end
$var wire 1 # clk $end
$var wire 16 @ in_B [15:0] $end
$var wire 1 , load $end
$var wire 1 / shift $end
$var reg 16 A s_B [15:0] $end
$upscope $end
$upscope $end
$upscope $end
$enddefinitions $end
$comment Show the parameter values. $end
$dumpall
b0 7
b1 6
b11 5
b10 4
$end
#0
$dumpvars
bx A
b0 @
bx ?
b0 >
b0 =
x<
x;
b0 :
b101001101010100010000010101001001010100 9
b0 8
03
02
01
b0 0
0/
x.
0-
0,
bx +
bx *
x)
x(
b0 '
0&
1%
0$
0#
b0 "
b0 !
$end
#10000
1#
#20000
0#
#30000
1#
#40000
0%
0#
#50000
1#
#60000
b1111111 '
b1111111 @
1$
b1111111 "
b11110111 !
b11110111 >
0#
#70000
1,
b1001100010011110100000101000100 9
b1 8
1#
#80000
1(
1.
0)
1;
1<
b11110111 +
b11110111 ?
b1111111 *
b1111111 A
0#
#90000
b1000011010011110100110101010000010101010101010001000101 9
1/
0,
b10 8
1#
#100000
1)
0(
b1 :
11
13
b111111 *
b111111 A
b1111011 +
b1111011 ?
0$
0#
#110000
1#
#120000
b111101 +
b111101 ?
b11111 *
b11111 A
01
b1000000000000000 0
b1000000000000000 =
b10 :
0#
#130000
1#
#140000
0)
0;
b11 :
b1100000000000000 0
b1100000000000000 =
b1111 *
b1111 A
b11110 +
b11110 ?
0#
#150000
1#
#160000
1)
1;
b1111 +
b1111 ?
b111 *
b111 A
b110000000000000 0
b110000000000000 =
b100 :
0#
#170000
1#
#180000
b101 :
b1011000000000000 0
b1011000000000000 =
b11 *
b11 A
b111 +
b111 ?
0#
#190000
1#
#200000
b11 +
b11 ?
b1 *
b1 A
b1101100000000000 0
b1101100000000000 =
b110 :
0#
#210000
1#
#220000
0)
0<
b111 :
b1110110000000000 0
b1110110000000000 =
b0 *
b0 A
b1 +
b1 ?
0#
#230000
1#
#240000
1(
0.
1)
0;
b0 +
b0 ?
b111011000000000 0
b111011000000000 =
b1000 :
0#
#250000
1#
#260000
0)
0(
b1001 :
b1011101100000000 0
b1011101100000000 =
11
03
0#
#270000
1#
#280000
01
b101110110000000 0
b101110110000000 =
b1010 :
0#
#290000
1#
#300000
b1011 :
b10111011000000 0
b10111011000000 =
0#
#310000
1#
#320000
b1011101100000 0
b1011101100000 =
b1100 :
0#
#330000
1#
#340000
b1101 :
b101110110000 0
b101110110000 =
0#
#350000
1#
#360000
b10111011000 0
b10111011000 =
b1110 :
0#
#370000
1#
#380000
b1111 :
b1011101100 0
b1011101100 =
0#
#390000
1#
#400000
b101110110 0
b101110110 =
1-
b10000 :
0#
#410000
0/
12
b10001010100111001000100 9
b11 8
1#
#420000
0#
#430000
1#
#440000
b1111111111001101 '
b1111111111001101 @
1$
1&
b110010 "
b1100100 !
b1100100 >
0#
#450000
b101001101010100010000010101001001010100 9
02
b0 8
1#
#460000
0#
#470000
1,
b1001100010011110100000101000100 9
b1 8
1#
#480000
1.
1<
0)
0(
b1100100 +
b1100100 ?
b1111111111001101 *
b1111111111001101 A
13
b0 0
b0 =
0-
b0 :
0$
0#
#490000
b1000011010011110100110101010000010101010101010001000101 9
1/
0,
b10 8
1#
#500000
1(
1)
0.
0<
b1 :
b111111111100110 *
b111111111100110 A
b110010 +
b110010 ?
0#
#510000
1#
#520000
1.
1;
1<
0)
1(
b11001 +
b11001 ?
b11111111110011 *
b11111111110011 A
03
11
b1000000000000000 0
b1000000000000000 =
b10 :
0#
#530000
1#
#540000
0)
0(
0;
b11 :
b100000000000000 0
b100000000000000 =
13
b1111111111001 *
b1111111111001 A
b1100 +
b1100 ?
0#
#550000
1#
#560000
1(
1)
0.
0<
b110 +
b110 ?
b111111111100 *
b111111111100 A
01
b10000000000000 0
b10000000000000 =
b100 :
0#
#570000
1#
#580000
1)
0(
1;
b101 :
b1001000000000000 0
b1001000000000000 =
11
03
b11111111110 *
b11111111110 A
b11 +
b11 ?
0#
#590000
1#
#600000
1(
1.
0)
1<
b1 +
b1 ?
b1111111111 *
b1111111111 A
01
b1100100000000000 0
b1100100000000000 =
b110 :
0#
#610000
1#
#620000
0)
0(
0;
b111 :
b110010000000000 0
b110010000000000 =
11
13
b111111111 *
b111111111 A
b0 +
b0 ?
0#
#630000
1#
#640000
b11111111 *
b11111111 A
01
b11001000000000 0
b11001000000000 =
b1000 :
0#
#650000
1#
#660000
b1001 :
b1100100000000 0
b1100100000000 =
b1111111 *
b1111111 A
0#
#670000
1#
#680000
b111111 *
b111111 A
b110010000000 0
b110010000000 =
b1010 :
0#
#690000
1#
#700000
b1011 :
b11001000000 0
b11001000000 =
b11111 *
b11111 A
0#
#710000
1#
#720000
b1111 *
b1111 A
b1100100000 0
b1100100000 =
b1100 :
0#
#730000
1#
#740000
b1101 :
b110010000 0
b110010000 =
b111 *
b111 A
0#
#750000
1#
#760000
b11 *
b11 A
b11001000 0
b11001000 =
b1110 :
0#
#770000
1#
#780000
b1111 :
b1100100 0
b1100100 =
b1 *
b1 A
0#
#790000
1#
#800000
1(
1)
0.
0<
b0 *
b0 A
b110010 0
b110010 =
1-
b10000 :
0#
#810000
0/
12
b10001010100111001000100 9
b11 8
1#
#820000
0#
#830000
1#
#840000
b1111111110011011 '
b1111111110011011 @
1$
b1100100 "
b110010 !
b110010 >
0#
#850000
b101001101010100010000010101001001010100 9
02
b0 8
1#
#860000
0#
#870000
1,
b1001100010011110100000101000100 9
b1 8
1#
#880000
0(
0)
1.
1<
b110010 +
b110010 ?
b1111111110011011 *
b1111111110011011 A
b0 0
b0 =
0-
b0 :
0$
0#
#890000
b1000011010011110100110101010000010101010101010001000101 9
1/
0,
b10 8
1#
#900000
1)
1;
b1 :
b111111111001101 *
b111111111001101 A
b11001 +
b11001 ?
0#
#910000
1#
#920000
1(
0.
0;
0<
b1100 +
b1100 ?
b11111111100110 *
b11111111100110 A
b1000000000000000 0
b1000000000000000 =
b10 :
0#
#930000
1#
#940000
1)
0(
1<
b11 :
b1100000000000000 0
b1100000000000000 =
11
03
b1111111110011 *
b1111111110011 A
b110 +
b110 ?
0#
#950000
1#
#960000
1(
1.
0)
1;
b11 +
b11 ?
b111111111001 *
b111111111001 A
01
b1110000000000000 0
b1110000000000000 =
b100 :
0#
#970000
1#
#980000
0)
0(
0<
b101 :
b111000000000000 0
b111000000000000 =
11
13
b11111111100 *
b11111111100 A
b1 +
b1 ?
0#
#990000
1#
#1000000
1(
0.
1)
0;
b0 +
b0 ?
b1111111110 *
b1111111110 A
01
b11100000000000 0
b11100000000000 =
b110 :
0#
#1010000
1#
#1020000
1)
0(
1<
b111 :
b1001110000000000 0
b1001110000000000 =
11
03
b111111111 *
b111111111 A
0#
#1030000
1#
#1040000
b11111111 *
b11111111 A
01
b1100111000000000 0
b1100111000000000 =
b1000 :
0#
#1050000
1#
#1060000
b1001 :
b1110011100000000 0
b1110011100000000 =
b1111111 *
b1111111 A
0#
#1070000
1#
#1080000
b111111 *
b111111 A
b1111001110000000 0
b1111001110000000 =
b1010 :
0#
#1090000
1#
#1100000
b1011 :
b1111100111000000 0
b1111100111000000 =
b11111 *
b11111 A
0#
#1110000
1#
#1120000
b1111 *
b1111 A
b1111110011100000 0
b1111110011100000 =
b1100 :
0#
#1130000
1#
#1140000
b1101 :
b1111111001110000 0
b1111111001110000 =
b111 *
b111 A
0#
#1150000
1#
#1160000
b11 *
b11 A
b1111111100111000 0
b1111111100111000 =
b1110 :
0#
#1170000
1#
#1180000
b1111 :
b1111111110011100 0
b1111111110011100 =
b1 *
b1 A
0#
#1190000
1#
#1200000
0)
0<
b0 *
b0 A
b1111111111001110 0
b1111111111001110 =
1-
b10000 :
0#
#1210000
0/
12
b10001010100111001000100 9
b11 8
1#
#1220000
0#
#1230000
1#
#1240000
b1 '
b1 @
1$
0&
b1 "
b1111111111111111 !
b1111111111111111 >
0#
#1250000
b101001101010100010000010101001001010100 9
02
b0 8
1#
#1260000
0#
#1270000
1,
b1001100010011110100000101000100 9
b1 8
1#
#1280000
1(
1.
1;
1<
b1111111111111111 +
b1111111111111111 ?
b1 *
b1 A
b0 0
b0 =
0-
b0 :
0$
0#
#1290000
b1000011010011110100110101010000010101010101010001000101 9
1/
0,
b10 8
1#
#1300000
0)
0(
0<
b1 :
11
13
b0 *
b0 A
b111111111111111 +
b111111111111111 ?
0#
#1310000
1#
#1320000
b11111111111111 +
b11111111111111 ?
01
b10 :
0#
#1330000
1#
#1340000
b11 :
b1111111111111 +
b1111111111111 ?
0#
#1350000
1#
#1360000
b111111111111 +
b111111111111 ?
b100 :
0#
#1370000
1#
#1380000
b101 :
b11111111111 +
b11111111111 ?
0#
#1390000
1#
#1400000
b1111111111 +
b1111111111 ?
b110 :
0#
#1410000
1#
#1420000
b111 :
b111111111 +
b111111111 ?
0#
#1430000
1#
#1440000
b11111111 +
b11111111 ?
b1000 :
0#
#1450000
1#
#1460000
b1001 :
b1111111 +
b1111111 ?
0#
#1470000
1#
#1480000
b111111 +
b111111 ?
b1010 :
0#
#1490000
1#
#1500000
b1011 :
b11111 +
b11111 ?
0#
#1510000
1#
#1520000
b1111 +
b1111 ?
b1100 :
0#
#1530000
1#
#1540000
b1101 :
b111 +
b111 ?
0#
#1550000
1#
#1560000
b11 +
b11 ?
b1110 :
0#
#1570000
1#
#1580000
b1111 :
b1 +
b1 ?
0#
#1590000
1#
#1600000
1(
0.
1)
0;
b0 +
b0 ?
1-
b10000 :
0#
#1610000
0/
12
b10001010100111001000100 9
b11 8
1#
#1620000
0#
#1630000
1#
#1640000
1$
b111111111111111 !
b111111111111111 >
0#
#1650000
b101001101010100010000010101001001010100 9
02
b0 8
1#
#1660000
0#
#1670000
1,
b1001100010011110100000101000100 9
b1 8
1#
#1680000
1.
1;
1<
0)
1(
b111111111111111 +
b111111111111111 ?
b1 *
b1 A
03
0-
b0 :
0$
0#
#1690000
b1000011010011110100110101010000010101010101010001000101 9
1/
0,
b10 8
1#
#1700000
0)
0(
0<
b1 :
11
13
b0 *
b0 A
b11111111111111 +
b11111111111111 ?
0#
#1710000
1#
#1720000
b1111111111111 +
b1111111111111 ?
01
b10 :
0#
#1730000
1#
#1740000
b11 :
b111111111111 +
b111111111111 ?
0#
#1750000
1#
#1760000
b11111111111 +
b11111111111 ?
b100 :
0#
#1770000
1#
#1780000
b101 :
b1111111111 +
b1111111111 ?
0#
#1790000
1#
#1800000
b111111111 +
b111111111 ?
b110 :
0#
#1810000
1#
#1820000
b111 :
b11111111 +
b11111111 ?
0#
#1830000
1#
#1840000
b1111111 +
b1111111 ?
b1000 :
0#
#1850000
1#
#1860000
b1001 :
b111111 +
b111111 ?
0#
#1870000
1#
#1880000
b11111 +
b11111 ?
b1010 :
0#
#1890000
1#
#1900000
b1011 :
b1111 +
b1111 ?
0#
#1910000
1#
#1920000
b111 +
b111 ?
b1100 :
0#
#1930000
1#
#1940000
b1101 :
b11 +
b11 ?
0#
#1950000
1#
#1960000
b1 +
b1 ?
b1110 :
0#
#1970000
1#
#1980000
1(
0.
1)
0;
b1111 :
b0 +
b0 ?
0#
#1990000
1#
#2000000
0)
0(
03
11
b1000000000000000 0
b1000000000000000 =
1-
b10000 :
0#
#2010000
0/
12
b10001010100111001000100 9
b11 8
1#
#2020000
0#
#2030000
1#
#2040000
b1111111111111110 '
b1111111111111110 @
1$
1&
b1000000000000000 !
b1000000000000000 >
0#
#2050000
b101001101010100010000010101001001010100 9
02
b0 8
1#
#2060000
0#
#2070000
1,
b1001100010011110100000101000100 9
b1 8
1#
#2080000
1)
1(
b1000000000000000 +
b1000000000000000 ?
b1111111111111110 *
b1111111111111110 A
13
01
b0 0
b0 =
0-
b0 :
0$
0#
#2090000
b1000011010011110100110101010000010101010101010001000101 9
1/
0,
b10 8
1#
#2100000
1)
0(
1<
b1 :
b1000000000000000 0
b1000000000000000 =
11
03
b111111111111111 *
b111111111111111 A
b100000000000000 +
b100000000000000 ?
0#
#2110000
1#
#2120000
b10000000000000 +
b10000000000000 ?
b11111111111111 *
b11111111111111 A
01
b1100000000000000 0
b1100000000000000 =
b10 :
0#
#2130000
1#
#2140000
b11 :
b1110000000000000 0
b1110000000000000 =
b1111111111111 *
b1111111111111 A
b1000000000000 +
b1000000000000 ?
0#
#2150000
1#
#2160000
b100000000000 +
b100000000000 ?
b111111111111 *
b111111111111 A
b1111000000000000 0
b1111000000000000 =
b100 :
0#
#2170000
1#
#2180000
b101 :
b1111100000000000 0
b1111100000000000 =
b11111111111 *
b11111111111 A
b10000000000 +
b10000000000 ?
0#
#2190000
1#
#2200000
b1000000000 +
b1000000000 ?
b1111111111 *
b1111111111 A
b1111110000000000 0
b1111110000000000 =
b110 :
0#
#2210000
1#
#2220000
b111 :
b1111111000000000 0
b1111111000000000 =
b111111111 *
b111111111 A
b100000000 +
b100000000 ?
0#
#2230000
1#
#2240000
b10000000 +
b10000000 ?
b11111111 *
b11111111 A
b1111111100000000 0
b1111111100000000 =
b1000 :
0#
#2250000
1#
#2260000
b1001 :
b1111111110000000 0
b1111111110000000 =
b1111111 *
b1111111 A
b1000000 +
b1000000 ?
0#
#2270000
1#
#2280000
b100000 +
b100000 ?
b111111 *
b111111 A
b1111111111000000 0
b1111111111000000 =
b1010 :
0#
#2290000
1#
#2300000
b1011 :
b1111111111100000 0
b1111111111100000 =
b11111 *
b11111 A
b10000 +
b10000 ?
0#
#2310000
1#
#2320000
b1000 +
b1000 ?
b1111 *
b1111 A
b1111111111110000 0
b1111111111110000 =
b1100 :
0#
#2330000
1#
#2340000
b1101 :
b1111111111111000 0
b1111111111111000 =
b111 *
b111 A
b100 +
b100 ?
0#
#2350000
1#
#2360000
b10 +
b10 ?
b11 *
b11 A
b1111111111111100 0
b1111111111111100 =
b1110 :
0#
#2370000
1#
#2380000
1(
1.
0)
1;
b1111 :
b1111111111111110 0
b1111111111111110 =
b1 *
b1 A
b1 +
b1 ?
0#
#2390000
1#
#2400000
0.
0;
0<
1)
1(
b0 +
b0 ?
b0 *
b0 A
13
11
b111111111111111 0
b111111111111111 =
1-
b10000 :
0#
#2410000
0/
12
b10001010100111001000100 9
b11 8
1#
